{"traitTreeId": 854, "className": "Demon Hunter", "classId": 12, "specName": "Devourer", "specId": 1480, "classNodes": [{"id": 90942, "name": "Vengeful Retreat", "type": "single", "posX": 2700, "posY": 1500, "maxRanks": 1, "entryNode": true, "next": [90930, 90941], "prev": [], "entries": [{"id": 112853, "definitionId": 117858, "maxRanks": 1, "type": "active", "name": "Vengeful Retreat", "spellId": 198793, "icon": "ability_demonhunter_vengefulretreat2", "index": 100}]}, {"id": 108723, "name": "Voidblade", "type": "single", "posX": 3900, "posY": 1500, "maxRanks": 1, "entryNode": true, "next": [90941, 90950], "prev": [], "entries": [{"id": 134272, "definitionId": 139045, "maxRanks": 1, "type": "active", "name": "Voidblade", "spellId": 1245412, "icon": "inv_12_voiddh_ability_voidblade", "index": 100}], "freeNode": true}, {"id": 90946, "name": "Sigil of Misery", "type": "single", "posX": 5100, "posY": 1500, "maxRanks": 1, "entryNode": true, "next": [90950, 90945], "prev": [], "entries": [{"id": 112859, "definitionId": 117864, "maxRanks": 1, "type": "active", "name": "Sigil of Misery", "spellId": 207684, "icon": "ability_demonhunter_sigilofmisery", "index": 100}]}, {"id": 90930, "name": "Vengeful Bonds", "type": "single", "posX": 2700, "posY": 2100, "maxRanks": 1, "next": [90931], "prev": [90942], "entries": [{"id": 112840, "definitionId": 117845, "maxRanks": 1, "type": "passive", "name": "Vengeful Bonds", "spellId": 320635, "icon": "ability_demonhunter_vengefulretreat2", "index": 100}]}, {"id": 90941, "name": "Unrestrained Fury", "type": "single", "posX": 3300, "posY": 2100, "maxRanks": 1, "next": [90931, 91007], "prev": [90942, 108723], "entries": [{"id": 112852, "definitionId": 117857, "maxRanks": 1, "type": "passive", "name": "Unrestrained Fury", "spellId": 320770, "icon": "ability_warrior_improveddisciplines", "index": 100}]}, {"id": 90950, "name": "Shattered Restoration", "type": "single", "posX": 4500, "posY": 2100, "maxRanks": 1, "next": [91007, 90948], "prev": [90946, 108723], "entries": [{"id": 112863, "definitionId": 117868, "maxRanks": 1, "type": "passive", "name": "Shattered Restoration", "spellId": 389824, "icon": "ability_warlock_soulsiphon", "index": 100}]}, {"id": 90945, "name": "Improved Sigil of Misery", "type": "single", "posX": 5100, "posY": 2100, "maxRanks": 1, "next": [90948], "prev": [90946], "entries": [{"id": 112858, "definitionId": 117863, "maxRanks": 1, "type": "passive", "name": "Improved Sigil of Misery", "spellId": 320418, "icon": "ability_demonhunter_sigilofmisery", "index": 100}]}, {"id": 90931, "name": "Bouncing Glaives", "type": "single", "posX": 2700, "posY": 2700, "maxRanks": 1, "next": [107347, 90938], "prev": [90941, 90930], "entries": [{"id": 112841, "definitionId": 117846, "maxRanks": 1, "type": "passive", "name": "Bouncing Glaives", "spellId": 320386, "icon": "ability_demonhunter_throwglaive", "index": 100}]}, {"id": 91007, "name": "Imprison", "type": "single", "posX": 3900, "posY": 2700, "maxRanks": 1, "next": [90938, 91006], "prev": [90950, 90941], "entries": [{"id": 112927, "definitionId": 117932, "maxRanks": 1, "type": "active", "name": "Imprison", "spellId": 217832, "icon": "ability_demonhunter_imprison", "index": 100}]}, {"id": 90948, "name": "Charred Warblades", "type": "single", "posX": 5100, "posY": 2700, "maxRanks": 1, "next": [91006, 90999], "prev": [90950, 90945], "entries": [{"id": 112861, "definitionId": 117866, "maxRanks": 1, "type": "passive", "name": "Charred Warblades", "spellId": 213010, "icon": "spell_fire_incinerate", "index": 100}]}, {"id": 107347, "name": "Void Nova", "type": "single", "posX": 2100, "posY": 3300, "maxRanks": 1, "next": [95154, 90994], "prev": [90931], "entries": [{"id": 132289, "definitionId": 137090, "maxRanks": 1, "type": "active", "name": "Void Nova", "spellId": 1234195, "icon": "inv_12_voiddh_ability_voidnova", "index": 100}]}, {"id": 90938, "name": "Improved Disrupt", "type": "single", "posX": 3300, "posY": 3300, "maxRanks": 1, "next": [90994, 90937, 95150], "prev": [90931, 91007], "entries": [{"id": 112849, "definitionId": 117854, "maxRanks": 1, "type": "passive", "name": "Improved Disrupt", "spellId": 320361, "icon": "ability_demonhunter_consumemagic", "index": 100}]}, {"id": 91006, "name": "Consume Magic", "type": "single", "posX": 4500, "posY": 3300, "maxRanks": 1, "next": [95150, 91005, 90933], "prev": [90948, 91007], "entries": [{"id": 112926, "definitionId": 117931, "maxRanks": 1, "type": "active", "name": "Consume Magic", "spellId": 278326, "icon": "spell_misc_zandalari_council_soulswap", "index": 100}]}, {"id": 90999, "name": "Aldrachi Design", "type": "single", "posX": 5700, "posY": 3300, "maxRanks": 1, "next": [90933, 95151], "prev": [90948], "entries": [{"id": 112917, "definitionId": 117922, "maxRanks": 1, "type": "passive", "name": "Aldrachi Design", "spellId": 391409, "icon": "inv_glaive_1h_artifactaldrochi_d_01dual", "index": 100}]}, {"id": 95154, "name": "Focused Ire", "type": "single", "posX": 2100, "posY": 3900, "reqPoints": 8, "maxRanks": 1, "next": [90940], "prev": [107347], "entries": [{"id": 117767, "definitionId": 122779, "maxRanks": 1, "type": "passive", "name": "Focused Ire", "spellId": 1266296, "icon": "ability_bossfellord_felspike", "index": 100}]}, {"id": 90994, "name": "Master of the Glaive / Champion of the Glaive", "type": "choice", "posX": 2700, "posY": 3900, "reqPoints": 8, "maxRanks": 1, "next": [90940, 90936], "prev": [90938, 107347], "entries": [{"id": 112912, "definitionId": 117917, "maxRanks": 1, "type": "passive", "name": "Master of the Glaive", "spellId": 389763, "icon": "inv_glaive_1h_demonhunter_a_01", "index": 100}, {"id": 117768, "definitionId": 122780, "maxRanks": 1, "type": "passive", "name": "Champion of the Glaive", "spellId": 429211, "icon": "inv_glaive_1h_battledungeon_c_01", "index": 200}]}, {"id": 90937, "name": "Disrupting Fury", "type": "single", "posX": 3300, "posY": 3900, "reqPoints": 8, "maxRanks": 1, "next": [90936], "prev": [90938], "entries": [{"id": 112848, "definitionId": 117853, "maxRanks": 1, "type": "passive", "name": "Disrupting Fury", "spellId": 183782, "icon": "ability_demonhunter_consumemagic", "index": 100}]}, {"id": 95150, "name": "Blazing Path", "type": "single", "posX": 3900, "posY": 3900, "reqPoints": 8, "maxRanks": 1, "next": [90936, 90939, 91004], "prev": [91006, 90938], "entries": [{"id": 117759, "definitionId": 122771, "maxRanks": 1, "type": "passive", "name": "Blazing Path", "spellId": 320416, "icon": "ability_demonhunter_felrush", "index": 100}]}, {"id": 91005, "name": "Swallowed Anger", "type": "single", "posX": 4500, "posY": 3900, "reqPoints": 8, "maxRanks": 1, "next": [], "prev": [91006], "entries": [{"id": 112925, "definitionId": 117930, "maxRanks": 1, "type": "passive", "name": "Swallowed Anger", "spellId": 320313, "icon": "spell_misc_zandalari_council_soulswap", "index": 100}]}, {"id": 90933, "name": "Aura of Pain", "type": "single", "posX": 5100, "posY": 3900, "reqPoints": 8, "maxRanks": 1, "next": [91004, 90927, 90947], "prev": [91006, 90999], "entries": [{"id": 112844, "definitionId": 117849, "maxRanks": 1, "type": "passive", "name": "Aura of Pain", "spellId": 207347, "icon": "spell_fire_felimmolation", "index": 100}]}, {"id": 95151, "name": "Live by the Glaive", "type": "single", "posX": 5700, "posY": 3900, "reqPoints": 8, "maxRanks": 1, "next": [90947], "prev": [90999], "entries": [{"id": 117761, "definitionId": 122773, "maxRanks": 1, "type": "passive", "name": "Live by the Glaive", "spellId": 428607, "icon": "inv_sword_108", "index": 100}]}, {"id": 90940, "name": "Pursuit", "type": "single", "posX": 2100, "posY": 4500, "reqPoints": 8, "maxRanks": 1, "next": [90935], "prev": [90994, 95154], "entries": [{"id": 112851, "definitionId": 117856, "maxRanks": 1, "type": "passive", "name": "Pursuit", "spellId": 320654, "icon": "ability_demonhunter_infernalstrike2", "index": 100}]}, {"id": 90936, "name": "Soul Rending", "type": "single", "posX": 3300, "posY": 4500, "reqPoints": 8, "maxRanks": 2, "next": [90935, 107346], "prev": [90994, 90937, 95150], "entries": [{"id": 112847, "definitionId": 117852, "maxRanks": 2, "type": "passive", "name": "Soul Rending", "spellId": 204909, "icon": "ability_demonhunter_soulcleave2", "index": 100}]}, {"id": 90939, "name": "Felfire Haste", "type": "single", "posX": 3900, "posY": 4500, "reqPoints": 8, "maxRanks": 1, "next": [107346], "prev": [95150], "entries": [{"id": 112850, "definitionId": 117855, "maxRanks": 1, "type": "passive", "name": "Felfire Haste", "spellId": 389846, "icon": "inv_boots_cloth_35v4", "index": 100}]}, {"id": 91004, "name": "Infernal Armor", "type": "single", "posX": 4500, "posY": 4500, "reqPoints": 8, "maxRanks": 2, "next": [107346, 91000], "prev": [90933, 95150], "entries": [{"id": 112924, "definitionId": 117929, "maxRanks": 2, "type": "passive", "name": "Infernal Armor", "spellId": 320331, "icon": "ability_demonhunter_immolation", "index": 100}]}, {"id": 90927, "name": "Burn It Out / Soul Cleanse", "type": "choice", "posX": 5100, "posY": 4500, "reqPoints": 8, "maxRanks": 1, "next": [91000], "prev": [90933], "entries": [{"id": 112837, "definitionId": 117842, "maxRanks": 1, "type": "passive", "name": "Burn It Out", "spellId": 1266316, "icon": "spell_fel_elementaldevastation", "index": 100}, {"id": 136502, "definitionId": 141275, "maxRanks": 1, "type": "passive", "name": "Soul Cleanse", "spellId": 1266496, "icon": "spell_nature_removecurse", "index": 200}]}, {"id": 90947, "name": "Lost in Darkness", "type": "single", "posX": 5700, "posY": 4500, "reqPoints": 8, "maxRanks": 1, "next": [91000], "prev": [95151, 90933], "entries": [{"id": 112860, "definitionId": 117865, "maxRanks": 1, "type": "passive", "name": "Lost in Darkness", "spellId": 389849, "icon": "inv_pet_inquisitoreye", "index": 100}]}, {"id": 90935, "name": "Illidari Knowledge", "type": "single", "posX": 2700, "posY": 5100, "reqPoints": 8, "maxRanks": 2, "next": [90934, 95152], "prev": [90936, 90940], "entries": [{"id": 112846, "definitionId": 117851, "maxRanks": 2, "type": "passive", "name": "Illidari Knowledge", "spellId": 389696, "icon": "spell_mage_overpowered", "index": 100}]}, {"id": 107346, "name": "Guile", "type": "single", "posX": 3900, "posY": 5100, "reqPoints": 8, "maxRanks": 1, "next": [95152, 90929], "prev": [90936, 90939, 91004], "entries": [{"id": 132288, "definitionId": 137089, "maxRanks": 1, "type": "passive", "name": "Guile", "spellId": 1223171, "icon": "spell_shadow_demonform", "index": 100}]}, {"id": 91000, "name": "Will of the Illidari", "type": "single", "posX": 5100, "posY": 5100, "reqPoints": 8, "maxRanks": 2, "next": [90929, 95149], "prev": [90947, 90927, 91004], "entries": [{"id": 112918, "definitionId": 117923, "maxRanks": 2, "type": "passive", "name": "Will of the Illidari", "spellId": 389695, "icon": "ability_demonhunter_spectank", "index": 100}]}, {"id": 90934, "name": "Internal Struggle", "type": "single", "posX": 2700, "posY": 5700, "reqPoints": 23, "maxRanks": 1, "next": [90996], "prev": [90935], "entries": [{"id": 112845, "definitionId": 117850, "maxRanks": 1, "type": "passive", "name": "Internal Struggle", "spellId": 393822, "icon": "ability_warlock_demonicpower", "index": 100}]}, {"id": 95152, "name": "Furious", "type": "single", "posX": 3300, "posY": 5700, "reqPoints": 23, "maxRanks": 1, "next": [110011, 91002], "prev": [107346, 90935], "entries": [{"id": 117762, "definitionId": 122774, "maxRanks": 1, "type": "passive", "name": "Furious", "spellId": 1266326, "icon": "ability_warlock_shadowfurytga", "index": 200}]}, {"id": 90929, "name": "Remorseless", "type": "single", "posX": 4500, "posY": 5700, "reqPoints": 23, "maxRanks": 1, "next": [91002, 90928], "prev": [91000, 107346], "entries": [{"id": 112839, "definitionId": 117844, "maxRanks": 1, "type": "passive", "name": "Remorseless", "spellId": 1266328, "icon": "inv_glaive_1h_npc_d_02", "index": 100}]}, {"id": 95149, "name": "First In, Last Out", "type": "single", "posX": 5100, "posY": 5700, "reqPoints": 23, "maxRanks": 1, "next": [90949], "prev": [91000], "entries": [{"id": 117758, "definitionId": 122770, "maxRanks": 1, "type": "passive", "name": "First In, Last Out", "spellId": 1266497, "icon": "ability_demonhunter_demonictrample", "index": 100}]}, {"id": 90996, "name": "Erratic Felheart", "type": "single", "posX": 2700, "posY": 6300, "reqPoints": 23, "maxRanks": 2, "next": [110010], "prev": [90934], "entries": [{"id": 112914, "definitionId": 117919, "maxRanks": 2, "type": "passive", "name": "Erratic Felheart", "spellId": 391397, "icon": "inv_archaeology_70_crystallineeyeofundravius", "index": 100}]}, {"id": 110011, "name": "Final Breath", "type": "single", "posX": 3300, "posY": 6300, "reqPoints": 23, "maxRanks": 1, "next": [], "prev": [95152], "entries": [{"id": 136501, "definitionId": 141274, "maxRanks": 1, "type": "passive", "name": "Final Breath", "spellId": 1266500, "icon": "spell_fire_felflamebreath", "index": 200}]}, {"id": 91002, "name": "Darkness", "type": "single", "posX": 3900, "posY": 6300, "reqPoints": 23, "maxRanks": 1, "next": [91001], "prev": [95152, 90929], "entries": [{"id": 112921, "definitionId": 117926, "maxRanks": 1, "type": "active", "name": "Darkness", "spellId": 196718, "icon": "ability_demonhunter_darkness", "index": 100}]}, {"id": 90928, "name": "Demon Muzzle", "type": "single", "posX": 4500, "posY": 6300, "reqPoints": 23, "maxRanks": 1, "next": [], "prev": [90929], "entries": [{"id": 112838, "definitionId": 117843, "maxRanks": 1, "type": "passive", "name": "Demon Muzzle", "spellId": 1266329, "icon": "spell_warlock_demonicservitude", "index": 100}]}, {"id": 90949, "name": "Soul Splitter", "type": "single", "posX": 5100, "posY": 6300, "reqPoints": 23, "maxRanks": 2, "next": [90997], "prev": [95149], "entries": [{"id": 112862, "definitionId": 117867, "maxRanks": 2, "type": "passive", "name": "Soul Splitter", "spellId": 1266330, "icon": "ability_warlock_soulswap", "index": 100}]}, {"id": 110010, "name": "Wings of Wrath", "type": "single", "posX": 2700, "posY": 6900, "reqPoints": 23, "maxRanks": 1, "next": [], "prev": [90996], "entries": [{"id": 136500, "definitionId": 141273, "maxRanks": 1, "type": "passive", "name": "Wings of Wrath", "spellId": 1266493, "icon": "ability_demonhunter_glide", "index": 100}]}, {"id": 91001, "name": "Long Night / Pitch Black", "type": "choice", "posX": 3900, "posY": 6900, "reqPoints": 23, "maxRanks": 1, "next": [], "prev": [91002], "entries": [{"id": 112920, "definitionId": 117925, "maxRanks": 1, "type": "passive", "name": "Long Night", "spellId": 389781, "icon": "spell_fire_twilightimmolation", "index": 100}, {"id": 112919, "definitionId": 117924, "maxRanks": 1, "type": "passive", "name": "Pitch Black", "spellId": 389783, "icon": "sha_spell_warlock_demonsoul", "index": 200}]}, {"id": 90997, "name": "Demonic Resilience", "type": "single", "posX": 5100, "posY": 6900, "reqPoints": 23, "maxRanks": 1, "next": [], "prev": [90949], "entries": [{"id": 117755, "definitionId": 122767, "maxRanks": 1, "type": "passive", "name": "Demonic Resilience", "spellId": 1266307, "icon": "inv_summondemonictyrant", "index": 200}]}], "specNodes": [{"id": 90912, "name": "", "type": "single", "posX": 16640, "posY": -320, "entryNode": true, "next": [], "prev": [], "entries": [{}]}, {"id": 107336, "name": "Void Ray", "type": "single", "posX": 12300, "posY": 1500, "maxRanks": 1, "entryNode": true, "next": [107344, 107771], "prev": [], "entries": [{"id": 132278, "definitionId": 137079, "maxRanks": 1, "type": "active", "name": "Void Ray", "spellId": 473728, "icon": "inv_12_dh_void_ability_voidray", "index": 100}]}, {"id": 107344, "name": "Soul Immolation", "type": "single", "posX": 11700, "posY": 2100, "maxRanks": 1, "next": [108727, 107340], "prev": [107336], "entries": [{"id": 132286, "definitionId": 137087, "maxRanks": 1, "type": "active", "name": "Soul Immolation", "spellId": 1241937, "icon": "inv_12_dh_void_ability_voidpurge", "index": 100}]}, {"id": 107771, "name": "Predator's Thirst", "type": "single", "posX": 12900, "posY": 2100, "maxRanks": 1, "next": [107340, 107343], "prev": [107336], "entries": [{"id": 133107, "definitionId": 137893, "maxRanks": 1, "type": "passive", "name": "Predator's Thirst", "spellId": 1215617, "icon": "inv_12_dh_void_ability_consume", "index": 100}]}, {"id": 108727, "name": "Tempered Soul / Spontaneous Immolation", "type": "choice", "posX": 11100, "posY": 2700, "maxRanks": 1, "next": [108726], "prev": [107344], "entries": [{"id": 134280, "definitionId": 139053, "maxRanks": 1, "type": "passive", "name": "Tempered Soul", "spellId": 1246555, "icon": "inv_12_dh_void_ability_voidpurge", "index": 100}, {"id": 135730, "definitionId": 140485, "maxRanks": 1, "type": "passive", "name": "Spontaneous Immolation", "spellId": 1246556, "icon": "spell_fire_twilightimmolation", "index": 200}]}, {"id": 107340, "name": "Void Metamorphosis", "type": "single", "posX": 12300, "posY": 2700, "maxRanks": 1, "next": [107339], "prev": [107344, 107771], "entries": [{"id": 132282, "definitionId": 137083, "maxRanks": 1, "type": "active", "name": "Void Metamorphosis", "spellId": 471306, "icon": "inv_112_ability_demonhunter_metamorphasisvoid", "index": 100}]}, {"id": 107343, "name": "Feast of Souls", "type": "single", "posX": 13500, "posY": 2700, "maxRanks": 1, "next": [107770], "prev": [107771], "entries": [{"id": 132285, "definitionId": 137086, "maxRanks": 1, "type": "passive", "name": "Feast of Souls", "spellId": 1237270, "icon": "inv_12_dh_void_ability_firstofsouls", "index": 100}]}, {"id": 108726, "name": "Scythe's Embrace / Duty Eternal", "type": "choice", "posX": 11100, "posY": 3300, "maxRanks": 1, "next": [107775, 108122], "prev": [108727], "entries": [{"id": 134279, "definitionId": 139052, "maxRanks": 1, "type": "passive", "name": "Scythe's Embrace", "spellId": 1246558, "icon": "inv_12_dh_void_ability_voidreaper", "index": 100}, {"id": 134275, "definitionId": 139048, "maxRanks": 1, "type": "passive", "name": "Duty Eternal", "spellId": 1246562, "icon": "inv_12_voiddh_ability_voidblade", "index": 200}]}, {"id": 107339, "name": "Collapsing Star", "type": "single", "posX": 12300, "posY": 3300, "maxRanks": 1, "next": [108122, 107999], "prev": [107340], "entries": [{"id": 132281, "definitionId": 137082, "maxRanks": 1, "type": "active", "name": "Collapsing Star", "spellId": 1221167, "icon": "inv_12_dh_void_ability_collapsingstar", "index": 100}]}, {"id": 107770, "name": "Moment of Craving", "type": "single", "posX": 13500, "posY": 3300, "maxRanks": 1, "next": [107999, 107342], "prev": [107343], "entries": [{"id": 133106, "definitionId": 137892, "maxRanks": 1, "type": "passive", "name": "Moment of Craving", "spellId": 1238488, "icon": "inv_12_dh_void_ability_momentofcraving", "index": 100}]}, {"id": 107775, "name": "Gift of the Void", "type": "single", "posX": 10500, "posY": 3900, "reqPoints": 8, "maxRanks": 1, "next": [108627, 107338], "prev": [108726], "entries": [{"id": 133111, "definitionId": 137897, "maxRanks": 1, "type": "passive", "name": "Gift of the Void", "spellId": 1272847, "icon": "ability_demonhunter_reversemagic", "index": 100}]}, {"id": 108122, "name": "Entropy", "type": "single", "posX": 11700, "posY": 3900, "reqPoints": 8, "maxRanks": 1, "next": [107338, 110009, 107997], "prev": [108726, 107339], "entries": [{"id": 133511, "definitionId": 138297, "maxRanks": 1, "type": "passive", "name": "Entropy", "spellId": 1261684, "icon": "inv_112_raidtrinkets_voidprism", "index": 100}]}, {"id": 107999, "name": "Waste Not", "type": "single", "posX": 12900, "posY": 3900, "reqPoints": 8, "maxRanks": 1, "next": [107997, 108144, 108628], "prev": [107770, 107339], "entries": [{"id": 133370, "definitionId": 138156, "maxRanks": 1, "type": "passive", "name": "Waste Not", "spellId": 1223918, "icon": "inv_12_dh_void_ability_wastenot", "index": 100}]}, {"id": 107342, "name": "Soulshaper", "type": "single", "posX": 14100, "posY": 3900, "reqPoints": 8, "maxRanks": 1, "next": [108628, 110174], "prev": [107770], "entries": [{"id": 132284, "definitionId": 137085, "maxRanks": 1, "type": "passive", "name": "Soulshaper", "spellId": 1238739, "icon": "inv_12_dh_void_ability_sunder", "index": 100}]}, {"id": 108627, "name": "Singed Spirit", "type": "single", "posX": 10500, "posY": 4500, "reqPoints": 8, "maxRanks": 1, "next": [108136], "prev": [107775], "entries": [{"id": 134148, "definitionId": 138928, "maxRanks": 1, "type": "passive", "name": "Singed Spirit", "spellId": 1272832, "icon": "inv_11_0_misc_candlekobold_color3", "index": 100}]}, {"id": 107338, "name": "Sweet Suffering", "type": "single", "posX": 11100, "posY": 4500, "reqPoints": 8, "maxRanks": 2, "next": [108136], "prev": [107775, 108122], "entries": [{"id": 132280, "definitionId": 137081, "maxRanks": 2, "type": "passive", "name": "Sweet Suffering", "spellId": 1244295, "icon": "ability_demonhunter_shatteredsouls", "index": 100}]}, {"id": 110009, "name": "Second Helping", "type": "single", "posX": 11700, "posY": 4500, "reqPoints": 8, "maxRanks": 1, "next": [108136, 109871], "prev": [108122], "entries": [{"id": 136499, "definitionId": 141272, "maxRanks": 1, "type": "passive", "name": "Second Helping", "spellId": 1239537, "icon": "inv_polearm_2h_voidscythe_d_01", "index": 100}]}, {"id": 107997, "name": "Umbral Blade", "type": "single", "posX": 12300, "posY": 4500, "reqPoints": 8, "maxRanks": 1, "next": [109871], "prev": [107999, 108122], "entries": [{"id": 133368, "definitionId": 138154, "maxRanks": 1, "type": "passive", "name": "Umbral Blade", "spellId": 1272842, "icon": "inv_12_dh_void_ability_reap", "index": 100}]}, {"id": 108144, "name": "Improved Consume", "type": "single", "posX": 12900, "posY": 4500, "reqPoints": 8, "maxRanks": 1, "next": [109871, 107774], "prev": [107999], "entries": [{"id": 134330, "definitionId": 139102, "maxRanks": 1, "type": "passive", "name": "Improved Consume", "spellId": 1272817, "icon": "inv_12_dh_void_ability_feast", "index": 200}]}, {"id": 108628, "name": "Sweet Release", "type": "single", "posX": 13500, "posY": 4500, "reqPoints": 8, "maxRanks": 2, "next": [107774], "prev": [107342, 107999], "entries": [{"id": 134149, "definitionId": 138929, "maxRanks": 2, "type": "passive", "name": "Sweet Release", "spellId": 1242768, "icon": "spell_misc_zandalari_council_soulswap", "index": 100}]}, {"id": 110174, "name": "Voidpurge", "type": "single", "posX": 14100, "posY": 4500, "reqPoints": 8, "maxRanks": 1, "next": [107774], "prev": [107342], "entries": [{"id": 136699, "definitionId": 141471, "maxRanks": 1, "type": "passive", "name": "Voidpurge", "spellId": 1244220, "icon": "inv_12_dh_void_ability_voidray", "index": 100}]}, {"id": 108136, "name": "Hungering Slash", "type": "single", "posX": 11100, "posY": 5100, "reqPoints": 8, "maxRanks": 1, "next": [110171, 110170, 110165], "prev": [108627, 107338, 110009], "entries": [{"id": 133531, "definitionId": 138317, "maxRanks": 1, "type": "active", "name": "Hungering Slash", "spellId": 1239519, "icon": "inv_12_dh_void_ability_reapersslice", "index": 100}]}, {"id": 109871, "name": "Voidrage", "type": "single", "posX": 12300, "posY": 5100, "reqPoints": 8, "maxRanks": 2, "next": [110165, 108143], "prev": [107997, 108144, 110009], "entries": [{"id": 136131, "definitionId": 140886, "maxRanks": 2, "type": "passive", "name": "Voidrage", "spellId": 1242956, "icon": "inv_12_dh_void_ability_soulimmolation", "index": 100}]}, {"id": 107774, "name": "Focused Ray", "type": "single", "posX": 13500, "posY": 5100, "reqPoints": 8, "maxRanks": 1, "next": [108143, 110169, 110168], "prev": [108144, 108628, 110174], "entries": [{"id": 133110, "definitionId": 137896, "maxRanks": 1, "type": "passive", "name": "Focused Ray", "spellId": 1240203, "icon": "inv_cosmicvoid_beam", "index": 100}]}, {"id": 110171, "name": "Soulforged Blades", "type": "single", "posX": 10500, "posY": 5700, "reqPoints": 20, "maxRanks": 1, "next": [110173], "prev": [108136], "entries": [{"id": 136696, "definitionId": 141468, "maxRanks": 1, "type": "passive", "name": "Soulforged Blades", "spellId": 1272432, "icon": "inv12_ability_deathknight_frostscythe", "index": 100}]}, {"id": 110170, "name": "Singular Strikes", "type": "single", "posX": 11100, "posY": 5700, "reqPoints": 20, "maxRanks": 1, "next": [110173], "prev": [108136], "entries": [{"id": 136695, "definitionId": 141467, "maxRanks": 1, "type": "passive", "name": "Singular Strikes", "spellId": 1272770, "icon": "inv_12_dh_void_ability_scythethrow", "index": 100}]}, {"id": 110165, "name": "Demonic Instinct", "type": "single", "posX": 11700, "posY": 5700, "reqPoints": 20, "maxRanks": 2, "next": [110167, 107341], "prev": [108136, 109871], "entries": [{"id": 136690, "definitionId": 141462, "maxRanks": 2, "type": "passive", "name": "Demonic Instinct", "spellId": 1247538, "icon": "inv_12_dh_void_ability_predatorsthirst", "index": 100}]}, {"id": 108143, "name": "Devourer's Edge", "type": "single", "posX": 12900, "posY": 5700, "reqPoints": 20, "maxRanks": 2, "next": [107341, 110166], "prev": [107774, 109871], "entries": [{"id": 133538, "definitionId": 138324, "maxRanks": 2, "type": "passive", "name": "Devourer's Edge", "spellId": 1244222, "icon": "inv_12_dh_void_ability_empoweredreap", "index": 100}]}, {"id": 110169, "name": "Voidglare Boon", "type": "single", "posX": 13500, "posY": 5700, "reqPoints": 20, "maxRanks": 1, "next": [110172], "prev": [107774], "entries": [{"id": 136694, "definitionId": 141466, "maxRanks": 1, "type": "passive", "name": "Voidglare Boon", "spellId": 1240202, "icon": "inv_nulllotus_cosmicvoid", "index": 100}]}, {"id": 110168, "name": "Rolling Torment", "type": "single", "posX": 14100, "posY": 5700, "reqPoints": 20, "maxRanks": 1, "next": [110172], "prev": [107774], "entries": [{"id": 136693, "definitionId": 141465, "maxRanks": 1, "type": "passive", "name": "Rolling Torment", "spellId": 1244237, "icon": "inv_cosmicvoid_debuff", "index": 100}]}, {"id": 110173, "name": "Voidrush", "type": "single", "posX": 11100, "posY": 6300, "reqPoints": 20, "maxRanks": 1, "next": [109503], "prev": [110171, 110170], "entries": [{"id": 136698, "definitionId": 141470, "maxRanks": 1, "type": "passive", "name": "Voidrush", "spellId": 1272422, "icon": "inv_12_dh_void_ability_voidstep", "index": 100}]}, {"id": 110167, "name": "Devourer's Bite", "type": "single", "posX": 11700, "posY": 6300, "reqPoints": 20, "maxRanks": 1, "next": [], "prev": [110165], "entries": [{"id": 136692, "definitionId": 141464, "maxRanks": 1, "type": "passive", "name": "Devourer's Bite", "spellId": 1240201, "icon": "inv_12_dh_void_ability_devourerbite", "index": 100}]}, {"id": 107341, "name": "Impending Apocalypse", "type": "single", "posX": 12300, "posY": 6300, "reqPoints": 20, "maxRanks": 1, "next": [108123], "prev": [110165, 108143], "entries": [{"id": 132283, "definitionId": 137084, "maxRanks": 1, "type": "passive", "name": "Impending Apocalypse", "spellId": 1227707, "icon": "inv_12_dh_void_ability_impendingapocalypse", "index": 100}]}, {"id": 110166, "name": "Calamitous", "type": "single", "posX": 12900, "posY": 6300, "reqPoints": 20, "maxRanks": 1, "next": [], "prev": [108143], "entries": [{"id": 136691, "definitionId": 141463, "maxRanks": 1, "type": "passive", "name": "Calamitous", "spellId": 1242495, "icon": "ability_argus_soulbombdebuffsmall", "index": 100}]}, {"id": 110172, "name": "Star Fragments", "type": "single", "posX": 13500, "posY": 6300, "reqPoints": 20, "maxRanks": 1, "next": [107345], "prev": [110168, 110169], "entries": [{"id": 136697, "definitionId": 141469, "maxRanks": 1, "type": "passive", "name": "Star Fragments", "spellId": 1240204, "icon": "inv_12_dh_void_ability_starfragments", "index": 100}]}, {"id": 109503, "name": "The Hunt", "type": "single", "posX": 11100, "posY": 6900, "reqPoints": 20, "maxRanks": 1, "next": [], "prev": [110173], "entries": [{"id": 135736, "definitionId": 140491, "maxRanks": 1, "type": "active", "name": "The Hunt", "spellId": 1246167, "icon": "inv_12_voiddh_ability_thehunt", "index": 100}]}, {"id": 108123, "name": "Emptiness / Soul Glutton", "type": "choice", "posX": 12300, "posY": 6900, "reqPoints": 20, "maxRanks": 1, "next": [], "prev": [107341], "entries": [{"id": 133512, "definitionId": 138298, "maxRanks": 1, "type": "passive", "name": "Emptiness", "spellId": 1242492, "icon": "inv_cosmicvoid_buff", "index": 100}, {"id": 134331, "definitionId": 139103, "maxRanks": 1, "type": "passive", "name": "Soul Glutton", "spellId": 1247534, "icon": "ability_bossgorefiend_gorefiendscorruption", "index": 200}]}, {"id": 107345, "name": "Eradicate", "type": "single", "posX": 13500, "posY": 6900, "reqPoints": 20, "maxRanks": 1, "next": [], "prev": [110172], "entries": [{"id": 132287, "definitionId": 137088, "maxRanks": 1, "type": "passive", "name": "Eradicate", "spellId": 1226033, "icon": "inv_12_dh_void_ability_eradicate", "index": 100}]}, {"id": 110416, "name": "Midnight / Midnight / Midnight", "type": "tiered", "posX": 12300, "posY": 7650, "reqPoints": 20, "maxRanks": 4, "entryNode": true, "next": [], "prev": [], "entries": [{"id": 137016, "definitionId": 141779, "maxRanks": 1, "type": "tierrank", "name": "Midnight", "spellId": 1242486, "icon": "inv12_apextalent_demonhunter_midnight", "index": 100}, {"id": 137015, "definitionId": 141778, "maxRanks": 2, "type": "tierrank", "name": "Midnight", "spellId": 1250088, "icon": "inv_ability_voidweaverpriest_entropicrift", "index": 200}, {"id": 137014, "definitionId": 141777, "maxRanks": 1, "type": "tierrank", "name": "Midnight", "spellId": 1250094, "icon": "ability_argus_edgeofobliteration", "index": 300}]}], "heroNodes": [{"id": 110112, "name": "Voidsurge", "type": "single", "posX": 8100, "posY": 1200, "maxRanks": 1, "entryNode": true, "subTreeId": 126, "next": [110114, 110113, 110117, 110105], "prev": [], "entries": [{"id": 136613, "definitionId": 141386, "maxRanks": 1, "type": "passive", "name": "Voidsurge", "spellId": 452402, "icon": "inv_ability_felscarreddemonhunter_demonsurge", "index": 100}], "freeNode": true}, {"id": 110114, "name": "Wave of Debilitation / Pursuit of Angriness", "type": "choice", "posX": 7200, "posY": 1800, "maxRanks": 1, "subTreeId": 126, "next": [110111], "prev": [110112], "entries": [{"id": 136621, "definitionId": 141394, "maxRanks": 1, "type": "passive", "name": "Wave of Debilitation", "spellId": 452403, "icon": "spell_fire_felfirenova", "index": 100}, {"id": 136619, "definitionId": 141392, "maxRanks": 1, "type": "passive", "name": "Pursuit of Angriness", "spellId": 452404, "icon": "ability_felarakkoa_focusedblast", "index": 200}]}, {"id": 110113, "name": "Focused Hatred", "type": "single", "posX": 7800, "posY": 1800, "maxRanks": 1, "subTreeId": 126, "next": [110115], "prev": [110112], "entries": [{"id": 136612, "definitionId": 141385, "maxRanks": 1, "type": "passive", "name": "Focused Hatred", "spellId": 452405, "icon": "ability_demonhunter_illidansgrasp", "index": 100}]}, {"id": 110117, "name": "Set Fire to the Pain / Improved Soul Rending", "type": "choice", "posX": 8400, "posY": 1800, "maxRanks": 1, "subTreeId": 126, "next": [110106], "prev": [110112], "entries": [{"id": 136620, "definitionId": 141393, "maxRanks": 1, "type": "passive", "name": "Set Fire to the Pain", "spellId": 452406, "icon": "ability_demonhunter_empowerwards", "index": 100}, {"id": 136618, "definitionId": 141391, "maxRanks": 1, "type": "passive", "name": "Improved Soul Rending", "spellId": 452407, "icon": "ability_demonhunter_soulcleave2", "index": 200}]}, {"id": 110105, "name": "Blind Focus", "type": "single", "posX": 9000, "posY": 1800, "maxRanks": 1, "subTreeId": 126, "next": [110108], "prev": [110112], "entries": [{"id": 136607, "definitionId": 141380, "maxRanks": 1, "type": "passive", "name": "Blind Focus", "spellId": 1272364, "icon": "inv_belt_leather_raiddemonhunter_r_01", "index": 100}]}, {"id": 110111, "name": "Burning Blades", "type": "single", "posX": 7200, "posY": 2400, "maxRanks": 1, "subTreeId": 126, "next": [110109], "prev": [110114], "entries": [{"id": 136610, "definitionId": 141383, "maxRanks": 1, "type": "passive", "name": "Burning Blades", "spellId": 452408, "icon": "inv_glaive_1h_artifactazgalor_d_02dual", "index": 100}]}, {"id": 110115, "name": "Violent Transformation", "type": "single", "posX": 7800, "posY": 2400, "maxRanks": 1, "subTreeId": 126, "next": [110107], "prev": [110113], "entries": [{"id": 136622, "definitionId": 141395, "maxRanks": 1, "type": "passive", "name": "Violent Transformation", "spellId": 452409, "icon": "spell_shadow_demoniccirclesummon", "index": 100}]}, {"id": 110106, "name": "Enduring Torment", "type": "single", "posX": 8400, "posY": 2400, "maxRanks": 1, "subTreeId": 126, "next": [110104], "prev": [110117], "entries": [{"id": 136615, "definitionId": 141388, "maxRanks": 1, "type": "passive", "name": "Enduring Torment", "spellId": 452410, "icon": "spell_fire_felimmolation", "index": 100}]}, {"id": 110108, "name": "Undying Embers", "type": "single", "posX": 9000, "posY": 2400, "maxRanks": 1, "subTreeId": 126, "next": [110110], "prev": [110105], "entries": [{"id": 136609, "definitionId": 141382, "maxRanks": 1, "type": "passive", "name": "Undying Embers", "spellId": 1272405, "icon": "ability_warlock_burningembersgreen", "index": 100}]}, {"id": 110109, "name": "Untethered Fury", "type": "single", "posX": 7200, "posY": 3000, "maxRanks": 1, "subTreeId": 126, "next": [110116], "prev": [110111], "entries": [{"id": 136606, "definitionId": 141379, "maxRanks": 1, "type": "passive", "name": "Untethered Fury", "spellId": 452411, "icon": "inv__felbarrage", "index": 100}]}, {"id": 110107, "name": "Student of Suffering / Flamebound", "type": "choice", "posX": 7800, "posY": 3000, "maxRanks": 1, "subTreeId": 126, "next": [110116], "prev": [110115], "entries": [{"id": 136616, "definitionId": 141389, "maxRanks": 1, "type": "passive", "name": "Student of Suffering", "spellId": 452412, "icon": "achievement_dungeon_theatreofpain_kultharok", "index": 100}, {"id": 136614, "definitionId": 141387, "maxRanks": 1, "type": "passive", "name": "Flamebound", "spellId": 452413, "icon": "spell_fire_felflamering", "index": 200}]}, {"id": 110104, "name": "Monster Rising", "type": "single", "posX": 8400, "posY": 3000, "maxRanks": 1, "subTreeId": 126, "next": [110116], "prev": [110106], "entries": [{"id": 136608, "definitionId": 141381, "maxRanks": 1, "type": "passive", "name": "Monster Rising", "spellId": 452414, "icon": "ability_warlock_demonicpower", "index": 100}]}, {"id": 110110, "name": "Volatile Instinct", "type": "single", "posX": 9000, "posY": 3000, "maxRanks": 1, "subTreeId": 126, "next": [110116], "prev": [110108], "entries": [{"id": 136611, "definitionId": 141384, "maxRanks": 1, "type": "passive", "name": "Volatile Instinct", "spellId": 1272453, "icon": "inv_nature_nova", "index": 100}]}, {"id": 110116, "name": "Demonic Intensity", "type": "single", "posX": 8100, "posY": 3600, "maxRanks": 1, "subTreeId": 126, "next": [], "prev": [110110, 110109, 110107, 110104], "entries": [{"id": 136617, "definitionId": 141390, "maxRanks": 1, "type": "passive", "name": "Demonic Intensity", "spellId": 452415, "icon": "spell_warlock_demonicempowerment", "index": 100}]}, {"id": 109449, "name": "Voidfall", "type": "single", "posX": 7800, "posY": 4200, "maxRanks": 1, "entryNode": true, "subTreeId": 124, "next": [109454, 109455, 109453, 109452], "prev": [], "entries": [{"id": 135667, "definitionId": 140423, "maxRanks": 1, "type": "passive", "name": "Voidfall", "spellId": 1253304, "icon": "inv_12_dh_void_ability_voidfall", "index": 100}], "freeNode": true}, {"id": 109454, "name": "Swift Erasure", "type": "single", "posX": 6900, "posY": 4800, "maxRanks": 1, "subTreeId": 124, "next": [109448], "prev": [109449], "entries": [{"id": 135672, "definitionId": 140428, "maxRanks": 1, "type": "passive", "name": "Swift Erasure", "spellId": 1253668, "icon": "ability_priest_darkarchangel", "index": 100}]}, {"id": 109455, "name": "Meteoric Rise", "type": "single", "posX": 7500, "posY": 4800, "maxRanks": 1, "subTreeId": 124, "next": [109447], "prev": [109449], "entries": [{"id": 135673, "definitionId": 140429, "maxRanks": 1, "type": "passive", "name": "Meteoric Rise", "spellId": 1253377, "icon": "ability_socererking_arcanefortification", "index": 100}]}, {"id": 109453, "name": "Catastrophe", "type": "single", "posX": 8100, "posY": 4800, "maxRanks": 1, "subTreeId": 124, "next": [109450], "prev": [109449], "entries": [{"id": 135671, "definitionId": 140427, "maxRanks": 1, "type": "passive", "name": "Catastrophe", "spellId": 1253769, "icon": "inv_netherportal", "index": 100}]}, {"id": 109452, "name": "Phase Shift", "type": "single", "posX": 8700, "posY": 4800, "maxRanks": 1, "subTreeId": 124, "next": [109451], "prev": [109449], "entries": [{"id": 135670, "definitionId": 140426, "maxRanks": 1, "type": "passive", "name": "Phase Shift", "spellId": 1256245, "icon": "ability_demonhunter_blur", "index": 100}]}, {"id": 109448, "name": "Path to Oblivion / State of Matter", "type": "choice", "posX": 6900, "posY": 5400, "maxRanks": 1, "subTreeId": 124, "next": [109445], "prev": [109454], "entries": [{"id": 135666, "definitionId": 140422, "maxRanks": 1, "type": "passive", "name": "Path to Oblivion", "spellId": 1253399, "icon": "ability_socererking_arcaneacceleration", "index": 100}, {"id": 135659, "definitionId": 140415, "maxRanks": 1, "type": "passive", "name": "State of Matter", "spellId": 1253402, "icon": "inv_112_arcane_buff", "index": 200}]}, {"id": 109447, "name": "Mass Acceleration", "type": "single", "posX": 7500, "posY": 5400, "maxRanks": 1, "subTreeId": 124, "next": [109446], "prev": [109455], "entries": [{"id": 135665, "definitionId": 140421, "maxRanks": 1, "type": "passive", "name": "Mass Acceleration", "spellId": 1256295, "icon": "inv_nullstone_cosmicvoid", "index": 100}]}, {"id": 109450, "name": "Doomsayer / Harness the Cosmos", "type": "choice", "posX": 8100, "posY": 5400, "maxRanks": 1, "subTreeId": 124, "next": [109444], "prev": [109453], "entries": [{"id": 135668, "definitionId": 140424, "maxRanks": 1, "type": "passive", "name": "Doomsayer", "spellId": 1253676, "icon": "inv_shadowflame_buff", "index": 100}, {"id": 136810, "definitionId": 141573, "maxRanks": 1, "type": "passive", "name": "Harness the Cosmos", "spellId": 1279247, "icon": "inv_cosmicvoid_orb", "index": 200}]}, {"id": 109451, "name": "Celestial Echoes", "type": "single", "posX": 8700, "posY": 5400, "maxRanks": 1, "subTreeId": 124, "next": [109443], "prev": [109452], "entries": [{"id": 135669, "definitionId": 140425, "maxRanks": 1, "type": "passive", "name": "Celestial Echoes", "spellId": 1253415, "icon": "inv_polearm_2h_voidscythe_d_01", "index": 100}]}, {"id": 109445, "name": "Final Hour", "type": "single", "posX": 6900, "posY": 6000, "maxRanks": 1, "subTreeId": 124, "next": [109442], "prev": [109448], "entries": [{"id": 135663, "definitionId": 140419, "maxRanks": 1, "type": "passive", "name": "Final Hour", "spellId": 1253805, "icon": "inv_10_worlddroplevelingoptionalreagent_relics_hourglass_color1", "index": 100}]}, {"id": 109446, "name": "Meteoric Fall", "type": "single", "posX": 7500, "posY": 6000, "maxRanks": 1, "subTreeId": 124, "next": [109442], "prev": [109447], "entries": [{"id": 135664, "definitionId": 140420, "maxRanks": 1, "type": "passive", "name": "Meteoric Fall", "spellId": 1253391, "icon": "ability_socererking_arcanereplication", "index": 100}]}, {"id": 109444, "name": "Dark Matter", "type": "single", "posX": 8100, "posY": 6000, "maxRanks": 1, "subTreeId": 124, "next": [109442], "prev": [109450], "entries": [{"id": 135662, "definitionId": 140418, "maxRanks": 1, "type": "passive", "name": "Dark Matter", "spellId": 1256307, "icon": "inv_cosmicvoid_nova", "index": 100}]}, {"id": 109443, "name": "Otherworldly Focus", "type": "single", "posX": 8700, "posY": 6000, "maxRanks": 1, "subTreeId": 124, "next": [109442], "prev": [109451], "entries": [{"id": 135661, "definitionId": 140417, "maxRanks": 1, "type": "passive", "name": "Otherworldly Focus", "spellId": 1253817, "icon": "inv_babyvoidwalker_blue", "index": 100}]}, {"id": 109442, "name": "World Killer", "type": "single", "posX": 7800, "posY": 6600, "maxRanks": 1, "subTreeId": 124, "next": [], "prev": [109443, 109444, 109446, 109445], "entries": [{"id": 135660, "definitionId": 140416, "maxRanks": 1, "type": "passive", "name": "World Killer", "spellId": 1256353, "icon": "inv_112_raiddimensius_brokenworld", "index": 100}]}], "subTreeNodes": [{"id": 108704, "name": "Annihilator / Void-Scarred", "type": "subtree", "posX": 7800, "posY": 600, "entryNode": true, "next": [], "prev": [], "entries": [{"id": 134251, "type": "subtree", "name": "Annihilator", "traitSubTreeId": 124, "traitTreeId": 854, "atlasMemberName": "talents-heroclass-demonhunter-annihilator", "nodes": [109449, 109454, 109455, 109453, 109452, 109448, 109447, 109450, 109451, 109445, 109446, 109444, 109443, 109442]}, {"id": 136623, "type": "subtree", "name": "Void-Scarred", "traitSubTreeId": 126, "traitTreeId": 854, "atlasMemberName": "talents-heroclass-demonhunter-felscarred2", "nodes": [110112, 110114, 110113, 110117, 110105, 110111, 110115, 110106, 110108, 110109, 110107, 110104, 110110, 110116]}]}], "fullNodeOrder": [90912, 90914, 90915, 90916, 90917, 90918, 90919, 90921, 90922, 90923, 90925, 90927, 90928, 90929, 90930, 90931, 90933, 90934, 90935, 90936, 90937, 90938, 90939, 90940, 90941, 90942, 90945, 90946, 90947, 90948, 90949, 90950, 90951, 90952, 90953, 90954, 90955, 90956, 90957, 90958, 90959, 90960, 90961, 90962, 90963, 90964, 90965, 90966, 90967, 90968, 90969, 90970, 90971, 90972, 90973, 90974, 90975, 90976, 90977, 90978, 90979, 90980, 90981, 90982, 90983, 90984, 90985, 90986, 90987, 90988, 90989, 90990, 90991, 90993, 90994, 90996, 90997, 90999, 91000, 91001, 91002, 91003, 91004, 91005, 91006, 91007, 91008, 91011, 91012, 91013, 91015, 91017, 91018, 91020, 91021, 91022, 91024, 91025, 91026, 91027, 91028, 91030, 91031, 91032, 91033, 91034, 91035, 91036, 93013, 93014, 93015, 93016, 94895, 94896, 94897, 94898, 94899, 94901, 94902, 94903, 94904, 94905, 94906, 94909, 94910, 94911, 94912, 94913, 94914, 94915, 94916, 94917, 94918, 94919, 95143, 95147, 95149, 95150, 95151, 95152, 95154, 99823, 99824, 107336, 107338, 107339, 107340, 107341, 107342, 107343, 107344, 107345, 107346, 107347, 107770, 107771, 107774, 107775, 107997, 107999, 108122, 108123, 108136, 108143, 108144, 108627, 108628, 108669, 108704, 108722, 108723, 108726, 108727, 108728, 108729, 109442, 109443, 109444, 109445, 109446, 109447, 109448, 109449, 109450, 109451, 109452, 109453, 109454, 109455, 109503, 109769, 109770, 109771, 109772, 109773, 109774, 109871, 110009, 110010, 110011, 110104, 110105, 110106, 110107, 110108, 110109, 110110, 110111, 110112, 110113, 110114, 110115, 110116, 110117, 110165, 110166, 110167, 110168, 110169, 110170, 110171, 110172, 110173, 110174, 110416, 110425, 110427]}