{"className": "Evoker", "classId": 13, "specName": "Devastation", "specId": 1467, "classNodes": [{"id": 30419, "name": "Landslide", "type": "single", "posX": 2700, "posY": 1500, "maxRanks": 1, "entryNode": true, "next": [30420], "entries": [{"id": 39947, "maxRanks": 1, "type": "active", "name": "Landslide", "spellId": 358385, "icon": "ability_earthen_pillar"}], "freeNode": true}, {"id": 30423, "name": "Obsidian Scales", "type": "single", "posX": 3900, "posY": 1500, "maxRanks": 1, "entryNode": true, "next": [30424], "entries": [{"id": 39951, "maxRanks": 1, "type": "active", "name": "Obsidian Scales", "spellId": 363916, "icon": "inv_artifact_dragonscales"}]}, {"id": 30436, "name": "Expunge", "type": "single", "posX": 5100, "posY": 1500, "maxRanks": 1, "entryNode": true, "next": [30435], "entries": [{"id": 39964, "maxRanks": 1, "type": "active", "name": "Expunge", "spellId": 365585, "icon": "ability_evoker_fontofmagic_green"}]}, {"id": 30420, "name": "Natural Convergence", "type": "single", "posX": 2700, "posY": 2100, "maxRanks": 1, "next": [30323, 30421, 30418], "entries": [{"id": 39948, "maxRanks": 1, "type": "passive", "name": "Natural Convergence", "spellId": 369913, "icon": "spell_frost_frostblast"}]}, {"id": 30424, "name": "Permeating Chill", "type": "single", "posX": 3900, "posY": 2100, "maxRanks": 1, "next": [30421, 30422, 30425], "entries": [{"id": 39952, "maxRanks": 1, "type": "passive", "name": "Permeating Chill", "spellId": 370897, "icon": "spell_frost_coldhearted"}]}, {"id": 30435, "name": "Rescue", "type": "single", "posX": 5100, "posY": 2100, "maxRanks": 1, "next": [30425, 30434, 30426], "entries": [{"id": 39963, "maxRanks": 1, "type": "active", "name": "Rescue", "spellId": 360995, "icon": "ability_evoker_rescue"}]}, {"id": 30323, "name": "Forger of Mountains", "type": "single", "posX": 2100, "posY": 2700, "maxRanks": 1, "next": [], "entries": [{"id": 39842, "maxRanks": 1, "type": "passive", "name": "Forger of Mountains", "spellId": 375528, "icon": "ability_earthen_pillar"}]}, {"id": 30421, "name": "Innate Magic", "type": "single", "posX": 3300, "posY": 2700, "maxRanks": 2, "next": [30418, 30413, 30322], "entries": [{"id": 39949, "maxRanks": 2, "type": "passive", "name": "Innate Magic", "spellId": 375520, "icon": "ability_evoker_innatemagic4"}]}, {"id": 30422, "name": "Obsidian Bulwark", "type": "single", "posX": 3900, "posY": 2700, "maxRanks": 1, "next": [], "entries": [{"id": 39950, "maxRanks": 1, "type": "passive", "name": "Obsidian Bulwark", "spellId": 375406, "icon": "inv_shield_1h_revenantfire_d_01"}]}, {"id": 30425, "name": "Enkindled", "type": "single", "posX": 4500, "posY": 2700, "maxRanks": 2, "next": [30322, 30324, 30426], "entries": [{"id": 39953, "maxRanks": 2, "type": "passive", "name": "Enkindled", "spellId": 375554, "icon": "ability_evoker_livingflame"}]}, {"id": 30434, "name": "Scarlet Adaptation", "type": "single", "posX": 5700, "posY": 2700, "maxRanks": 1, "next": [], "entries": [{"id": 39962, "maxRanks": 1, "type": "passive", "name": "Scarlet Adaptation", "spellId": 372469, "icon": "inv_bijou_red"}]}, {"id": 30418, "name": "Quell", "type": "single", "posX": 2700, "posY": 3300, "maxRanks": 1, "next": [30417, 30415], "entries": [{"id": 39946, "maxRanks": 1, "type": "active", "name": "Quell", "spellId": 351338, "icon": "ability_evoker_quell"}]}, {"id": 30413, "name": "Recall", "type": "single", "posX": 3300, "posY": 3300, "maxRanks": 1, "next": [30414], "entries": [{"id": 39941, "maxRanks": 1, "type": "passive", "name": "Recall", "spellId": 371806, "icon": "ability_evoker_recall"}]}, {"id": 30322, "name": "Clobbering Sweep / Heavy Wingbeats", "type": "choice", "posX": 3900, "posY": 3300, "maxRanks": 1, "next": [], "entries": [{"id": 39840, "maxRanks": 1, "type": "passive", "name": "Clobbering Sweep", "spellId": 375443, "icon": "ability_racial_tailswipe"}, {"id": 39841, "maxRanks": 1, "type": "passive", "name": "Heavy Wingbeats", "spellId": 368838, "icon": "ability_racial_wingbuffet"}]}, {"id": 30324, "name": "Tailwind", "type": "single", "posX": 4500, "posY": 3300, "maxRanks": 1, "next": [30325], "entries": [{"id": 39843, "maxRanks": 1, "type": "passive", "name": "Tailwind", "spellId": 375556, "icon": "ability_skyreach_wind"}]}, {"id": 30426, "name": "Cauterizing Flame", "type": "single", "posX": 5100, "posY": 3300, "maxRanks": 1, "next": [30427, 30326], "entries": [{"id": 39954, "maxRanks": 1, "type": "active", "name": "Cauterizing Flame", "spellId": 374251, "icon": "ability_evoker_fontofmagic_red"}]}, {"id": 30417, "name": "Roar of Exhilaration", "type": "single", "posX": 2100, "posY": 3900, "reqPoints": 8, "maxRanks": 1, "next": [], "entries": [{"id": 39945, "maxRanks": 1, "type": "passive", "name": "Roar of Exhilaration", "spellId": 375507, "icon": "ability_hunter_mastertactitian"}]}, {"id": 30415, "name": "Suffused With Power", "type": "single", "posX": 2700, "posY": 3900, "reqPoints": 8, "maxRanks": 2, "next": [30416], "entries": [{"id": 39943, "maxRanks": 2, "type": "passive", "name": "Suffused With Power", "spellId": 376164, "icon": "spell_arcane_studentofmagic"}]}, {"id": 30433, "name": "Tip the Scales", "type": "single", "posX": 3900, "posY": 3900, "reqPoints": 8, "maxRanks": 1, "entryNode": true, "next": [30414, 30432, 30325], "entries": [{"id": 39961, "maxRanks": 1, "type": "active", "name": "Tip the Scales", "spellId": 370553, "icon": "ability_evoker_tipthescales"}]}, {"id": 30427, "name": "Attuned to the Dream", "type": "single", "posX": 5100, "posY": 3900, "reqPoints": 8, "maxRanks": 2, "next": [30428], "entries": [{"id": 39955, "maxRanks": 2, "type": "passive", "name": "Attuned to the Dream", "spellId": 376930, "icon": "ability_rogue_imrovedrecuperate"}]}, {"id": 30326, "name": "Sleep Walk", "type": "single", "posX": 5700, "posY": 3900, "reqPoints": 8, "maxRanks": 1, "next": [], "entries": [{"id": 39845, "maxRanks": 1, "type": "active", "name": "Sleep Walk", "spellId": 360806, "icon": "ability_xavius_dreamsimulacrum"}]}, {"id": 30414, "name": "Draconic Legacy", "type": "single", "posX": 3300, "posY": 4500, "reqPoints": 8, "maxRanks": 2, "next": [30416, 30412], "entries": [{"id": 39942, "maxRanks": 2, "type": "passive", "name": "Draconic Legacy", "spellId": 376166, "icon": "inv_helm_mail_dracthyrquest_b_02"}]}, {"id": 30432, "name": "Tempered Scales", "type": "single", "posX": 3900, "posY": 4500, "reqPoints": 8, "maxRanks": 2, "next": [30431], "entries": [{"id": 39960, "maxRanks": 2, "type": "passive", "name": "Tempered Scales", "spellId": 375544, "icon": "inv_misc_rubysanctum1"}]}, {"id": 30325, "name": "Extended Flight", "type": "single", "posX": 4500, "posY": 4500, "reqPoints": 8, "maxRanks": 2, "next": [30429], "entries": [{"id": 39844, "maxRanks": 2, "type": "passive", "name": "Extended Flight", "spellId": 375517, "icon": "ability_evoker_hover"}]}, {"id": 30428, "name": "Bountiful Bloom", "type": "single", "posX": 5100, "posY": 4500, "reqPoints": 8, "maxRanks": 1, "next": [30429], "entries": [{"id": 39956, "maxRanks": 1, "type": "passive", "name": "Bountiful Bloom", "spellId": 370886, "icon": "ability_evoker_emeraldblossom"}]}, {"id": 30416, "name": "Blast Furnace", "type": "single", "posX": 2700, "posY": 5100, "reqPoints": 8, "maxRanks": 2, "next": [30408, 30407, 30411], "entries": [{"id": 39944, "maxRanks": 2, "type": "passive", "name": "Blast Furnace", "spellId": 375510, "icon": "ability_evoker_firebreath"}]}, {"id": 30412, "name": "Exuberance", "type": "single", "posX": 3300, "posY": 5100, "reqPoints": 8, "maxRanks": 1, "next": [30411], "entries": [{"id": 39940, "maxRanks": 1, "type": "passive", "name": "Exuberance", "spellId": 375542, "icon": "achievement_guildperk_mountup"}]}, {"id": 30431, "name": "Source of Magic", "type": "single", "posX": 3900, "posY": 5100, "reqPoints": 8, "maxRanks": 1, "next": [30411, 30430, 30405], "entries": [{"id": 39959, "maxRanks": 1, "type": "active", "name": "Source of Magic", "spellId": 369459, "icon": "ability_evoker_blue_01"}]}, {"id": 30429, "name": "Ancient Flame", "type": "single", "posX": 5100, "posY": 5100, "reqPoints": 8, "maxRanks": 1, "next": [30430, 30399, 30400], "entries": [{"id": 39957, "maxRanks": 1, "type": "passive", "name": "Ancient Flame", "spellId": 369990, "icon": "inv_elemental_mote_fire01"}]}, {"id": 30408, "name": "Unravel", "type": "single", "posX": 2100, "posY": 5700, "reqPoints": 20, "maxRanks": 1, "next": [30409], "entries": [{"id": 39936, "maxRanks": 1, "type": "active", "name": "Unravel", "spellId": 368432, "icon": "ability_evoker_unravel"}]}, {"id": 30407, "name": "Protracted Talons", "type": "single", "posX": 2700, "posY": 5700, "reqPoints": 20, "maxRanks": 1, "next": [30409], "entries": [{"id": 39935, "maxRanks": 1, "type": "passive", "name": "Protracted Talons", "spellId": 369909, "icon": "ability_evoker_azurestrike"}]}, {"id": 30411, "name": "Oppressing Roar", "type": "single", "posX": 3300, "posY": 5700, "reqPoints": 20, "maxRanks": 1, "next": [30409, 30410, 30405], "entries": [{"id": 39939, "maxRanks": 1, "type": "active", "name": "Oppressing Roar", "spellId": 372048, "icon": "ability_evoker_oppressingroar"}]}, {"id": 30430, "name": "Fly With Me", "type": "single", "posX": 4500, "posY": 5700, "reqPoints": 20, "maxRanks": 1, "next": [30405, 30403], "entries": [{"id": 39958, "maxRanks": 1, "type": "active", "name": "Fly With Me", "spellId": 370665, "icon": "ability_evoker_flywithme"}]}, {"id": 30399, "name": "Lush Growth", "type": "single", "posX": 5100, "posY": 5700, "reqPoints": 20, "maxRanks": 2, "next": [30402], "entries": [{"id": 39926, "maxRanks": 2, "type": "passive", "name": "Lush Growth", "spellId": 375561, "icon": "inv_staff_2h_bloodelf_c_01"}]}, {"id": 30400, "name": "Renewing Blaze", "type": "single", "posX": 5700, "posY": 5700, "reqPoints": 20, "maxRanks": 1, "next": [30401], "entries": [{"id": 39927, "maxRanks": 1, "type": "active", "name": "Renewing Blaze", "spellId": 374348, "icon": "ability_evoker_masterylifebinder_red"}]}, {"id": 30409, "name": "Leaping Flames", "type": "single", "posX": 2700, "posY": 6300, "reqPoints": 20, "maxRanks": 1, "next": [30406], "entries": [{"id": 39937, "maxRanks": 1, "type": "passive", "name": "Leaping Flames", "spellId": 369939, "icon": "spell_fire_flare"}]}, {"id": 30410, "name": "Overawe", "type": "single", "posX": 3300, "posY": 6300, "reqPoints": 20, "maxRanks": 1, "next": [], "entries": [{"id": 39938, "maxRanks": 1, "type": "passive", "name": "Overawe", "spellId": 374346, "icon": "ability_evoker_oppressingroar2"}]}, {"id": 30405, "name": "Aerial Mastery", "type": "single", "posX": 3900, "posY": 6300, "reqPoints": 20, "maxRanks": 1, "next": [30404], "entries": [{"id": 39933, "maxRanks": 1, "type": "passive", "name": "Aerial Mastery", "spellId": 365933, "icon": "ability_evoker_aerialmastery"}]}, {"id": 30403, "name": "Twin Guardian", "type": "single", "posX": 4500, "posY": 6300, "reqPoints": 20, "maxRanks": 1, "next": [30402], "entries": [{"id": 39931, "maxRanks": 1, "type": "passive", "name": "Twin Guardian", "spellId": 370888, "icon": "ability_skyreach_shielded"}]}, {"id": 30401, "name": "Fire Within / Pyrexia", "type": "choice", "posX": 5700, "posY": 6300, "reqPoints": 20, "maxRanks": 1, "next": [30402], "entries": [{"id": 39928, "maxRanks": 1, "type": "passive", "name": "Fire Within", "spellId": 375577, "icon": "item_sparkofragnoros"}, {"id": 39929, "maxRanks": 1, "type": "passive", "name": "Pyrexia", "spellId": 375574, "icon": "spell_fire_incinerate"}]}, {"id": 30406, "name": "Terror of the Skies", "type": "single", "posX": 2700, "posY": 6900, "reqPoints": 20, "maxRanks": 1, "next": [], "entries": [{"id": 39934, "maxRanks": 1, "type": "passive", "name": "Terror of the Skies", "spellId": 371032, "icon": "ability_evoker_terroroftheskies"}]}, {"id": 30404, "name": "Time Spiral", "type": "single", "posX": 3900, "posY": 6900, "reqPoints": 20, "maxRanks": 1, "next": [], "entries": [{"id": 39932, "maxRanks": 1, "type": "active", "name": "Time Spiral", "spellId": 374968, "icon": "ability_evoker_timespiral"}]}, {"id": 30402, "name": "Zephyr", "type": "single", "posX": 5100, "posY": 6900, "reqPoints": 20, "maxRanks": 1, "next": [], "entries": [{"id": 39930, "maxRanks": 1, "type": "active", "name": "Zephyr", "spellId": 374227, "icon": "ability_evoker_hoverblack"}]}], "specNodes": [{"id": 30321, "name": "", "type": "single", "posX": 16600, "posY": -300, "maxRanks": 0, "entryNode": true, "next": [], "entries": [{"id": 39839, "maxRanks": 0, "type": null, "icon": ""}]}, {"id": 30393, "name": "Pyre", "type": "single", "posX": 11700, "posY": 1500, "maxRanks": 1, "entryNode": true, "next": [30394, 30392], "entries": [{"id": 39919, "maxRanks": 1, "type": "active", "name": "Pyre", "spellId": 357211, "icon": "ability_evoker_pyre"}]}, {"id": 30394, "name": "Ruby Essence Burst", "type": "single", "posX": 11100, "posY": 2100, "maxRanks": 1, "next": [30367, 30395], "entries": [{"id": 39920, "maxRanks": 1, "type": "passive", "name": "Ruby Essence Burst", "spellId": 376872, "icon": "ability_evoker_essenceburst4"}]}, {"id": 30392, "name": "Azure Essence Burst", "type": "single", "posX": 12300, "posY": 2100, "maxRanks": 1, "next": [30395, 30391], "entries": [{"id": 39918, "maxRanks": 1, "type": "passive", "name": "Azure Essence Burst", "spellId": 375721, "icon": "ability_evoker_essenceburst2"}]}, {"id": 30367, "name": "Volatility", "type": "single", "posX": 11100, "posY": 2700, "maxRanks": 2, "next": [30396], "entries": [{"id": 39891, "maxRanks": 2, "type": "passive", "name": "Volatility", "spellId": 369089, "icon": "spell_fire_ragnaros_lavabolt"}]}, {"id": 30395, "name": "Arcane Intensity", "type": "single", "posX": 11700, "posY": 2700, "maxRanks": 2, "next": [30396, 30390], "entries": [{"id": 39921, "maxRanks": 2, "type": "passive", "name": "Arcane Intensity", "spellId": 375618, "icon": "ability_evoker_disintegrate"}]}, {"id": 30391, "name": "Lay Waste", "type": "single", "posX": 12300, "posY": 2700, "maxRanks": 2, "next": [30390], "entries": [{"id": 39917, "maxRanks": 2, "type": "passive", "name": "Lay Waste", "spellId": 371034, "icon": "ability_evoker_deepbreath"}]}, {"id": 30396, "name": "Dense Energy", "type": "single", "posX": 11100, "posY": 3300, "maxRanks": 1, "next": [30397, 30387], "entries": [{"id": 39922, "maxRanks": 1, "type": "passive", "name": "Dense Energy", "spellId": 370962, "icon": "ability_evoker_pyre"}]}, {"id": 30390, "name": "Essence Attunement", "type": "single", "posX": 12300, "posY": 3300, "maxRanks": 1, "next": [30387, 30389], "entries": [{"id": 39916, "maxRanks": 1, "type": "passive", "name": "Essence Attunement", "spellId": 375722, "icon": "ability_evoker_essenceburststacks"}]}, {"id": 30397, "name": "Ruby Affinity", "type": "single", "posX": 10500, "posY": 3900, "reqPoints": 8, "maxRanks": 2, "next": [30386, 30398], "entries": [{"id": 39923, "maxRanks": 2, "type": "passive", "name": "Ruby Affinity", "spellId": 376889, "icon": "inv_elemental_primal_fire"}]}, {"id": 30387, "name": "Dragonrage", "type": "single", "posX": 11700, "posY": 3900, "reqPoints": 8, "maxRanks": 1, "next": [30386, 30364, 30388], "entries": [{"id": 39913, "maxRanks": 1, "type": "active", "name": "Dragonrage", "spellId": 375087, "icon": "ability_evoker_dragonrage"}]}, {"id": 30389, "name": "Azure Affinity", "type": "single", "posX": 12900, "posY": 3900, "reqPoints": 8, "maxRanks": 2, "next": [30388, 30374], "entries": [{"id": 39915, "maxRanks": 2, "type": "passive", "name": "Azure Affinity", "spellId": 376890, "icon": "inv_misc_lesseressence"}]}, {"id": 30398, "name": "Engulfing Blaze / Ruby Embers", "type": "choice", "posX": 9900, "posY": 4500, "reqPoints": 8, "maxRanks": 1, "next": [30383, 30381, 30365], "entries": [{"id": 39924, "maxRanks": 1, "type": "passive", "name": "Engulfing Blaze", "spellId": 370837, "icon": "inv_inscription_pigment_ruby"}, {"id": 39925, "maxRanks": 1, "type": "passive", "name": "Ruby Embers", "spellId": 365937, "icon": "inv_tradeskillitem_lessersorcerersfire"}]}, {"id": 30386, "name": "Imminent Destruction", "type": "single", "posX": 11100, "posY": 4500, "reqPoints": 8, "maxRanks": 1, "next": [30383, 30385], "entries": [{"id": 39912, "maxRanks": 1, "type": "passive", "name": "Imminent Destruction", "spellId": 370781, "icon": "spell_burningbladeshaman_blazing_radiance"}]}, {"id": 30364, "name": "Animosity", "type": "single", "posX": 11700, "posY": 4500, "reqPoints": 8, "maxRanks": 1, "next": [], "entries": [{"id": 39888, "maxRanks": 1, "type": "passive", "name": "Animosity", "spellId": 375797, "icon": "spell_nature_shamanrage"}]}, {"id": 30388, "name": "Power Swell", "type": "single", "posX": 12300, "posY": 4500, "reqPoints": 8, "maxRanks": 1, "next": [30385, 30375], "entries": [{"id": 39914, "maxRanks": 1, "type": "passive", "name": "Power Swell", "spellId": 370839, "icon": "ability_evoker_powerswell"}]}, {"id": 30374, "name": "Eternity Surge", "type": "single", "posX": 13500, "posY": 4500, "reqPoints": 8, "maxRanks": 1, "next": [30375, 30373, 30371], "entries": [{"id": 39900, "maxRanks": 1, "type": "active", "name": "Eternity Surge", "spellId": 359073, "icon": "ability_evoker_eternitysurge"}]}, {"id": 30381, "name": "Firestorm", "type": "single", "posX": 9300, "posY": 5100, "reqPoints": 8, "maxRanks": 1, "next": [30380, 30382], "entries": [{"id": 39907, "maxRanks": 1, "type": "active", "name": "Firestorm", "spellId": 368847, "icon": "ability_evoker_firestorm"}]}, {"id": 30365, "name": "Cascading Power", "type": "single", "posX": 9900, "posY": 5100, "reqPoints": 8, "maxRanks": 1, "next": [], "entries": [{"id": 39889, "maxRanks": 1, "type": "passive", "name": "Cascading Power", "spellId": 375796, "icon": "ability_evoker_innatemagic2"}]}, {"id": 30383, "name": "Font of Magic", "type": "single", "posX": 10500, "posY": 5100, "reqPoints": 8, "maxRanks": 1, "next": [30384, 30382], "entries": [{"id": 39909, "maxRanks": 1, "type": "passive", "name": "Font of Magic", "spellId": 375783, "icon": "ability_evoker_fontofmagic"}]}, {"id": 30385, "name": "Imposing Presence", "type": "single", "posX": 11700, "posY": 5100, "reqPoints": 8, "maxRanks": 1, "next": [30384, 30376], "entries": [{"id": 39911, "maxRanks": 1, "type": "passive", "name": "Imposing Presence", "spellId": 371016, "icon": "ability_evoker_quell"}]}, {"id": 30375, "name": "Power Nexus", "type": "single", "posX": 12900, "posY": 5100, "reqPoints": 8, "maxRanks": 1, "next": [30376, 30372], "entries": [{"id": 39901, "maxRanks": 1, "type": "passive", "name": "Power Nexus", "spellId": 369908, "icon": "ability_evoker_powernexus"}]}, {"id": 30373, "name": "Causality / Continuum", "type": "choice", "posX": 13500, "posY": 5100, "reqPoints": 8, "maxRanks": 1, "next": [], "entries": [{"id": 39898, "maxRanks": 1, "type": "passive", "name": "Causality", "spellId": 375777, "icon": "spell_azerite_essence_16"}, {"id": 39899, "maxRanks": 1, "type": "passive", "name": "Continuum", "spellId": 369375, "icon": "ability_socererking_arcanewrath"}]}, {"id": 30371, "name": "Charged Blast", "type": "single", "posX": 14100, "posY": 5100, "reqPoints": 8, "maxRanks": 1, "next": [30372, 30370], "entries": [{"id": 39896, "maxRanks": 1, "type": "active", "name": "Charged Blast", "spellId": 370452, "icon": "ability_evoker_chargedblast"}]}, {"id": 30380, "name": "Snapfire", "type": "single", "posX": 9300, "posY": 5700, "reqPoints": 20, "maxRanks": 1, "next": [], "entries": [{"id": 39906, "maxRanks": 1, "type": "passive", "name": "Snapfire", "spellId": 370783, "icon": "spell_shaman_improvedfirenova"}]}, {"id": 30382, "name": "Feed the Flames", "type": "single", "posX": 9900, "posY": 5700, "reqPoints": 20, "maxRanks": 1, "next": [30378], "entries": [{"id": 39908, "maxRanks": 1, "type": "passive", "name": "Feed the Flames", "spellId": 369846, "icon": "mace_1h_blacksmithing_d_04_icon"}]}, {"id": 30384, "name": "Heat Wave", "type": "single", "posX": 11100, "posY": 5700, "reqPoints": 20, "maxRanks": 2, "next": [30378, 30377], "entries": [{"id": 39910, "maxRanks": 2, "type": "passive", "name": "Heat Wave", "spellId": 375725, "icon": "spell_fire_moltenblood"}]}, {"id": 30376, "name": "Honed Aggression", "type": "single", "posX": 12300, "posY": 5700, "reqPoints": 20, "maxRanks": 2, "next": [30377, 30369], "entries": [{"id": 39902, "maxRanks": 2, "type": "passive", "name": "Honed Aggression", "spellId": 371038, "icon": "spell_fire_blueimmolation"}]}, {"id": 30372, "name": "Eternity's Span", "type": "single", "posX": 13500, "posY": 5700, "reqPoints": 20, "maxRanks": 1, "next": [30369], "entries": [{"id": 39897, "maxRanks": 1, "type": "passive", "name": "Eternity's Span", "spellId": 375757, "icon": "spell_arcane_arcanetorrent"}]}, {"id": 30370, "name": "Arcane Reverberation / Expansive Maw", "type": "choice", "posX": 14100, "posY": 5700, "reqPoints": 20, "maxRanks": 1, "next": [], "entries": [{"id": 39894, "maxRanks": 1, "type": "passive", "name": "Arcane Reverberation", "spellId": 376159, "icon": "ability_monk_forcesphere"}, {"id": 39895, "maxRanks": 1, "type": "passive", "name": "Expansive Maw", "spellId": 376156, "icon": "inv_misc_head_dragon_blue"}]}, {"id": 30378, "name": "Burnout", "type": "single", "posX": 10500, "posY": 6300, "reqPoints": 20, "maxRanks": 2, "next": [30379], "entries": [{"id": 39904, "maxRanks": 2, "type": "passive", "name": "Burnout", "spellId": 375801, "icon": "spell_fire_soulburn"}]}, {"id": 30377, "name": "Ruin", "type": "single", "posX": 11700, "posY": 6300, "reqPoints": 20, "maxRanks": 1, "next": [30366], "entries": [{"id": 39903, "maxRanks": 1, "type": "passive", "name": "Ruin", "spellId": 376888, "icon": "ability_evoker_dragonrage2"}]}, {"id": 30369, "name": "Focusing Iris", "type": "single", "posX": 12900, "posY": 6300, "reqPoints": 20, "maxRanks": 2, "next": [30368], "entries": [{"id": 39893, "maxRanks": 2, "type": "passive", "name": "Focusing Iris", "spellId": 370843, "icon": "spell_mage_temporalshield"}]}, {"id": 30379, "name": "Everburning Flame", "type": "single", "posX": 10500, "posY": 6900, "reqPoints": 20, "maxRanks": 1, "next": [], "entries": [{"id": 39905, "maxRanks": 1, "type": "passive", "name": "Everburning Flame", "spellId": 370819, "icon": "spell_fire_burnout"}]}, {"id": 30366, "name": "Tyranny", "type": "single", "posX": 11700, "posY": 6900, "reqPoints": 20, "maxRanks": 2, "next": [], "entries": [{"id": 39890, "maxRanks": 2, "type": "passive", "name": "Tyranny", "spellId": 370845, "icon": "spell_shaman_shockinglava"}]}, {"id": 30368, "name": "Scintillation", "type": "single", "posX": 12900, "posY": 6900, "reqPoints": 20, "maxRanks": 1, "next": [], "entries": [{"id": 39892, "maxRanks": 1, "type": "passive", "name": "Scintillation", "spellId": 370821, "icon": "spell_arcane_arcane03"}]}]}