{"traitTreeId": 786, "className": "Shaman", "classId": 7, "specName": "Elemental", "specId": 262, "classNodes": [{"id": 103588, "name": "Chain Heal", "type": "single", "posX": 1800, "posY": 1200, "maxRanks": 1, "entryNode": true, "next": [103596], "prev": [], "entries": [{"id": 127861, "definitionId": 132670, "maxRanks": 1, "type": "active", "name": "Chain Heal", "spellId": 1064, "icon": "spell_nature_healingwavegreater", "index": 100}]}, {"id": 103598, "name": "Lava Burst", "type": "single", "posX": 3000, "posY": 1200, "maxRanks": 1, "entryNode": true, "next": [103596, 103615, 103605], "prev": [], "entries": [{"id": 127873, "definitionId": 132682, "maxRanks": 1, "type": "active", "name": "Lava Burst", "spellId": 51505, "icon": "spell_shaman_lavaburst", "index": 100}], "freeNode": true}, {"id": 103616, "name": "Astral Shift", "type": "single", "posX": 4200, "posY": 1200, "maxRanks": 1, "entryNode": true, "next": [103615, 103611, 103581], "prev": [], "entries": [{"id": 127893, "definitionId": 132702, "maxRanks": 1, "type": "active", "name": "Astral Shift", "spellId": 108271, "icon": "ability_shaman_astralshift", "index": 100}]}, {"id": 103583, "name": "Chain Lightning", "type": "single", "posX": 6000, "posY": 1200, "maxRanks": 1, "entryNode": true, "next": [103604, 103614, 103582], "prev": [], "entries": [{"id": 127856, "definitionId": 132665, "maxRanks": 1, "type": "active", "name": "Chain Lightning", "spellId": 188443, "icon": "spell_nature_chainlightning", "index": 100}], "freeNode": true}, {"id": 103596, "name": "Earth Shield", "type": "single", "posX": 2400, "posY": 1800, "maxRanks": 1, "next": [103602, 103590], "prev": [103588, 103598], "entries": [{"id": 127871, "definitionId": 132680, "maxRanks": 1, "type": "active", "name": "Earth Shield", "spellId": 974, "icon": "spell_nature_skinofearth", "index": 100}]}, {"id": 103615, "name": "Wind Shear", "type": "single", "posX": 3600, "posY": 1800, "maxRanks": 1, "next": [103605, 103610, 103579], "prev": [103598, 103616], "entries": [{"id": 127892, "definitionId": 132701, "maxRanks": 1, "type": "active", "name": "Wind Shear", "spellId": 57994, "icon": "spell_nature_cyclone", "index": 100}]}, {"id": 103611, "name": "Planes Traveler / Astral Bulwark", "type": "choice", "posX": 4200, "posY": 1800, "maxRanks": 1, "next": [103579], "prev": [103616], "entries": [{"id": 127888, "definitionId": 132697, "maxRanks": 1, "type": "passive", "name": "Planes Traveler", "spellId": 381647, "icon": "spell_shaman_astralshift", "index": 200}, {"id": 127887, "definitionId": 132696, "maxRanks": 1, "type": "passive", "name": "Astral Bulwark", "spellId": 377933, "icon": "spell_shaman_ancestralawakening", "index": 300}]}, {"id": 103581, "name": "Spirit Wolf / Thunderous Paws", "type": "choice", "posX": 4800, "posY": 1800, "maxRanks": 1, "next": [103579, 103591], "prev": [103616], "entries": [{"id": 127854, "definitionId": 132663, "maxRanks": 1, "type": "passive", "name": "Spirit Wolf", "spellId": 260878, "icon": "spell_hunter_lonewolf", "index": 100}, {"id": 127853, "definitionId": 132662, "maxRanks": 1, "type": "passive", "name": "Thunderous Paws", "spellId": 378075, "icon": "ability_hunter_longevity", "index": 200}]}, {"id": 103604, "name": "Frost Shock", "type": "single", "posX": 5400, "posY": 1800, "maxRanks": 1, "next": [103591, 103619], "prev": [103583], "entries": [{"id": 127879, "definitionId": 132688, "maxRanks": 1, "type": "active", "name": "Frost Shock", "spellId": 196840, "icon": "spell_frost_frostshock", "index": 100}]}, {"id": 103614, "name": "Winds of Al'Akir", "type": "single", "posX": 6600, "posY": 1800, "maxRanks": 1, "next": [103585], "prev": [103583], "entries": [{"id": 127891, "definitionId": 132700, "maxRanks": 1, "type": "passive", "name": "Winds of Al'Akir", "spellId": 382215, "icon": "ability_druid_galewinds", "index": 100}]}, {"id": 103602, "name": "Elemental Orbit", "type": "single", "posX": 1800, "posY": 2400, "maxRanks": 1, "next": [103594], "prev": [103596], "entries": [{"id": 127877, "definitionId": 132686, "maxRanks": 1, "type": "passive", "name": "Elemental Orbit", "spellId": 383010, "icon": "ability_mage_shattershield", "index": 100}]}, {"id": 103605, "name": "Fire and Ice", "type": "single", "posX": 3000, "posY": 2400, "maxRanks": 1, "next": [103590, 103617, 103608], "prev": [103598, 103615], "entries": [{"id": 127880, "definitionId": 132689, "maxRanks": 1, "type": "passive", "name": "Fire and Ice", "spellId": 382886, "icon": "spell_firefrost-orb", "index": 100}]}, {"id": 103610, "name": "Ancestral Wolf Affinity", "type": "single", "posX": 3600, "posY": 2400, "maxRanks": 1, "next": [103617], "prev": [103615], "entries": [{"id": 127886, "definitionId": 132695, "maxRanks": 1, "type": "passive", "name": "Ancestral Wolf Affinity", "spellId": 382197, "icon": "spell_beastmaster_wolf", "index": 100}]}, {"id": 103579, "name": "Capacitor Totem", "type": "single", "posX": 4200, "posY": 2400, "maxRanks": 1, "next": [103617, 103618], "prev": [103581, 103611, 103615], "entries": [{"id": 127851, "definitionId": 132660, "maxRanks": 1, "type": "active", "name": "Capacitor Totem", "spellId": 192058, "icon": "spell_nature_brilliance", "index": 100}]}, {"id": 103591, "name": "Spirit Walk / Gust of Wind", "type": "choice", "posX": 4800, "posY": 2400, "maxRanks": 1, "next": [103624, 103613], "prev": [103581, 103604], "entries": [{"id": 127865, "definitionId": 132674, "maxRanks": 1, "type": "active", "name": "Spirit Walk", "spellId": 58875, "icon": "ability_tracking", "index": 100}, {"id": 127864, "definitionId": 132673, "maxRanks": 1, "type": "active", "name": "Gust of Wind", "spellId": 192063, "icon": "inv_misc_volatileair", "index": 200}]}, {"id": 103619, "name": "Encasing Cold / Arctic Snowstorm", "type": "choice", "posX": 5400, "posY": 2400, "maxRanks": 1, "next": [103624], "prev": [103604], "entries": [{"id": 127898, "definitionId": 132707, "maxRanks": 1, "type": "passive", "name": "Encasing Cold", "spellId": 462762, "icon": "ability_mage_coldasice", "index": 100}, {"id": 127897, "definitionId": 132706, "maxRanks": 1, "type": "passive", "name": "Arctic Snowstorm", "spellId": 462764, "icon": "spell_frost_glacier", "index": 200}]}, {"id": 103582, "name": "Brimming with Life", "type": "single", "posX": 6000, "posY": 2400, "maxRanks": 1, "next": [103624, 103585, 103622], "prev": [103583], "entries": [{"id": 127855, "definitionId": 132664, "maxRanks": 1, "type": "passive", "name": "Brimming with Life", "spellId": 381689, "icon": "inv_jewelry_talisman_06", "index": 100}]}, {"id": 103590, "name": "Healing Stream Totem", "type": "single", "posX": 2400, "posY": 3000, "maxRanks": 1, "next": [103601, 103608], "prev": [103596, 103605], "entries": [{"id": 127863, "definitionId": 132672, "maxRanks": 1, "type": "active", "name": "Healing Stream Totem", "spellId": 392915, "visibleSpellId": 5394, "icon": "inv_spear_04", "index": 100}]}, {"id": 103617, "name": "Earthgrab Totem", "type": "single", "posX": 3600, "posY": 3000, "maxRanks": 1, "next": [103608, 103593], "prev": [103579, 103605, 103610], "entries": [{"id": 127894, "definitionId": 132703, "maxRanks": 1, "type": "active", "name": "Earthgrab Totem", "spellId": 51485, "icon": "spell_nature_stranglevines", "index": 100}]}, {"id": 103618, "name": "Static Charge / Guardian's Cudgel", "type": "choice", "posX": 4200, "posY": 3000, "maxRanks": 1, "next": [103593, 103613, 103623], "prev": [103579], "entries": [{"id": 127896, "definitionId": 132705, "maxRanks": 1, "type": "passive", "name": "Static Charge", "spellId": 265046, "icon": "spell_nature_brilliance", "index": 100}, {"id": 127895, "definitionId": 132704, "maxRanks": 1, "type": "passive", "name": "Guardian's Cudgel", "spellId": 381819, "icon": "inv_mace_2h_draenorcrafted_d_01_b_alliance", "index": 200}]}, {"id": 103624, "name": "Purge / Greater Purge", "type": "choice", "posX": 5400, "posY": 3000, "maxRanks": 1, "next": [103613, 103622], "prev": [103619, 103591, 103582], "entries": [{"id": 127905, "definitionId": 132714, "maxRanks": 1, "type": "active", "name": "Purge", "spellId": 370, "icon": "spell_nature_purge", "index": 100}, {"id": 127904, "definitionId": 132713, "maxRanks": 1, "type": "active", "name": "Greater Purge", "spellId": 378773, "icon": "spell_shaman_focusedstrikes", "index": 200}]}, {"id": 103585, "name": "Earth Elemental", "type": "single", "posX": 6600, "posY": 3000, "maxRanks": 1, "next": [103622, 103612], "prev": [103614, 103582], "entries": [{"id": 127858, "definitionId": 132667, "maxRanks": 1, "type": "active", "name": "Earth Elemental", "spellId": 198103, "icon": "spell_nature_earthelemental_totem", "index": 100}]}, {"id": 103601, "name": "Elemental Resistance", "type": "single", "posX": 2400, "posY": 3600, "reqPoints": 8, "maxRanks": 1, "next": [103594, 103597], "prev": [103590], "entries": [{"id": 127876, "definitionId": 132685, "maxRanks": 1, "type": "passive", "name": "Elemental Resistance", "spellId": 462368, "icon": "spell_fireresistancetotem_01", "index": 100}]}, {"id": 103608, "name": "Cleanse Spirit", "type": "single", "posX": 3000, "posY": 3600, "reqPoints": 8, "maxRanks": 1, "next": [103597], "prev": [103590, 103617, 103605], "entries": [{"id": 127884, "definitionId": 132693, "maxRanks": 1, "type": "active", "name": "Cleanse Spirit", "spellId": 51886, "icon": "ability_shaman_cleansespirit", "index": 100}]}, {"id": 103593, "name": "Tremor Totem", "type": "single", "posX": 3600, "posY": 3600, "reqPoints": 8, "maxRanks": 1, "next": [103597, 103623], "prev": [103618, 103617], "entries": [{"id": 127868, "definitionId": 132677, "maxRanks": 1, "type": "active", "name": "Tremor Totem", "spellId": 8143, "icon": "spell_nature_tremortotem", "index": 100}]}, {"id": 103613, "name": "Nature's Guardian", "type": "single", "posX": 4800, "posY": 3600, "reqPoints": 8, "maxRanks": 1, "next": [103623, 103627, 103625], "prev": [103624, 103618, 103591], "entries": [{"id": 127890, "definitionId": 132699, "maxRanks": 1, "type": "passive", "name": "Nature's Guardian", "spellId": 30884, "icon": "spell_nature_natureguardian", "index": 100}]}, {"id": 103622, "name": "Nature's Fury", "type": "single", "posX": 6000, "posY": 3600, "reqPoints": 8, "maxRanks": 1, "next": [103627, 103606], "prev": [103585, 103624, 103582], "entries": [{"id": 127902, "definitionId": 132711, "maxRanks": 1, "type": "passive", "name": "Nature's Fury", "spellId": 381655, "icon": "spell_nature_spiritarmor", "index": 100}]}, {"id": 103594, "name": "Refreshing Waters", "type": "single", "posX": 1800, "posY": 4200, "reqPoints": 8, "maxRanks": 1, "next": [103584], "prev": [103601, 103602], "entries": [{"id": 127869, "definitionId": 132678, "maxRanks": 1, "type": "passive", "name": "Refreshing Waters", "spellId": 378211, "icon": "ability_shaman_fortifyingwaters", "index": 100}]}, {"id": 103597, "name": "Elemental Warding", "type": "single", "posX": 3000, "posY": 4200, "reqPoints": 8, "maxRanks": 1, "next": [103584, 103810, 103603], "prev": [103608, 103593, 103601], "entries": [{"id": 127872, "definitionId": 132681, "maxRanks": 1, "type": "passive", "name": "Elemental Warding", "spellId": 381650, "icon": "inv_10_elementalcombinedfoozles_primordial", "index": 100}]}, {"id": 103623, "name": "Hex", "type": "single", "posX": 4200, "posY": 4200, "reqPoints": 8, "maxRanks": 1, "next": [103603, 103600, 103625], "prev": [103593, 103613, 103618], "entries": [{"id": 127903, "definitionId": 132712, "maxRanks": 1, "type": "active", "name": "Hex", "spellId": 51514, "icon": "spell_shaman_hex", "index": 100}]}, {"id": 103627, "name": "Wind Rush Totem", "type": "single", "posX": 5400, "posY": 4200, "reqPoints": 8, "maxRanks": 1, "next": [103625, 103607, 103606], "prev": [103622, 103613], "entries": [{"id": 127909, "definitionId": 132718, "maxRanks": 1, "type": "active", "name": "Wind Rush Totem", "spellId": 192077, "icon": "ability_shaman_windwalktotem", "index": 200}]}, {"id": 103612, "name": "Primordial Bond", "type": "single", "posX": 6600, "posY": 4200, "reqPoints": 8, "maxRanks": 1, "next": [103606], "prev": [103585], "entries": [{"id": 127889, "definitionId": 132698, "maxRanks": 1, "type": "passive", "name": "Primordial Bond", "spellId": 381764, "icon": "inv_elemental_primal_earth", "index": 100}]}, {"id": 103584, "name": "Spiritwalker's Grace", "type": "single", "posX": 2400, "posY": 4800, "reqPoints": 8, "maxRanks": 1, "next": [103626, 103589], "prev": [103597, 103594], "entries": [{"id": 127857, "definitionId": 132666, "maxRanks": 1, "type": "active", "name": "Spiritwalker's Grace", "spellId": 79206, "icon": "spell_shaman_spiritwalkersgrace", "index": 100}]}, {"id": 103810, "name": "Ancestral Guidance", "type": "single", "posX": 3000, "posY": 4800, "reqPoints": 8, "maxRanks": 1, "next": [103589], "prev": [103597], "entries": [{"id": 128116, "definitionId": 132925, "maxRanks": 1, "type": "active", "name": "Ancestral Guidance", "spellId": 108281, "icon": "ability_shaman_ancestralguidance", "index": 100}]}, {"id": 103603, "name": "Thunderstorm", "type": "single", "posX": 3600, "posY": 4800, "reqPoints": 8, "maxRanks": 1, "next": [103589, 103586, 103621], "prev": [103597, 103623], "entries": [{"id": 127878, "definitionId": 132687, "maxRanks": 1, "type": "active", "name": "Thunderstorm", "spellId": 51490, "icon": "spell_shaman_thunderstorm", "index": 100}]}, {"id": 103600, "name": "Voodoo Mastery", "type": "single", "posX": 4200, "posY": 4800, "reqPoints": 8, "maxRanks": 1, "next": [103586], "prev": [103623], "entries": [{"id": 127875, "definitionId": 132684, "maxRanks": 1, "type": "passive", "name": "Voodoo Mastery", "spellId": 204268, "icon": "spell_shaman_hex", "index": 100}]}, {"id": 103625, "name": "Totemic Focus", "type": "single", "posX": 4800, "posY": 4800, "reqPoints": 8, "maxRanks": 1, "next": [103586, 103599, 103609], "prev": [103627, 103623, 103613], "entries": [{"id": 127906, "definitionId": 132715, "maxRanks": 1, "type": "passive", "name": "Totemic Focus", "spellId": 382201, "icon": "inv_relics_totemofrebirth", "index": 100}]}, {"id": 103607, "name": "Ascending Air / Jet Stream", "type": "choice", "posX": 5400, "posY": 4800, "reqPoints": 8, "maxRanks": 1, "next": [103599], "prev": [103627], "entries": [{"id": 127883, "definitionId": 132692, "maxRanks": 1, "type": "passive", "name": "Ascending Air", "spellId": 462791, "icon": "achievement_raidprimalist_windelemental", "index": 100}, {"id": 127882, "definitionId": 132691, "maxRanks": 1, "type": "passive", "name": "Jet Stream", "spellId": 462817, "icon": "inv_elemental_primal_air", "index": 200}]}, {"id": 103606, "name": "Enhanced Imbues", "type": "single", "posX": 6000, "posY": 4800, "reqPoints": 8, "maxRanks": 1, "next": [103599, 103628], "prev": [103622, 103612, 103627], "entries": [{"id": 127881, "definitionId": 132690, "maxRanks": 1, "type": "passive", "name": "Enhanced Imbues", "spellId": 462796, "icon": "spell_nature_rockbiter", "index": 100}]}, {"id": 103626, "name": "Graceful Spirit / Spiritwalker's Aegis", "type": "choice", "posX": 1800, "posY": 5400, "reqPoints": 20, "maxRanks": 1, "next": [103587, 103620], "prev": [103584], "entries": [{"id": 127908, "definitionId": 132717, "maxRanks": 1, "type": "passive", "name": "Graceful Spirit", "spellId": 192088, "icon": "spell_shaman_spectraltransformation", "index": 100}, {"id": 127907, "definitionId": 132716, "maxRanks": 1, "type": "passive", "name": "Spiritwalker's Aegis", "spellId": 378077, "icon": "ability_racial_forceshield", "index": 200}]}, {"id": 103589, "name": "Lightning Lasso", "type": "single", "posX": 3000, "posY": 5400, "reqPoints": 20, "maxRanks": 1, "next": [103587], "prev": [103603, 103584, 103810], "entries": [{"id": 127862, "definitionId": 132671, "maxRanks": 1, "type": "active", "name": "Lightning Lasso", "spellId": 305483, "icon": "shaman_pvp_lightninglasso", "index": 300}]}, {"id": 103586, "name": "Totemic Projection", "type": "single", "posX": 4200, "posY": 5400, "reqPoints": 20, "maxRanks": 1, "next": [103609, 103629], "prev": [103603, 103625, 103600], "entries": [{"id": 127859, "definitionId": 132668, "maxRanks": 1, "type": "active", "name": "Totemic Projection", "spellId": 108287, "icon": "ability_shaman_totemrelocation", "index": 100}]}, {"id": 103599, "name": "Totemic Surge", "type": "single", "posX": 5400, "posY": 5400, "reqPoints": 20, "maxRanks": 1, "next": [103609, 103595], "prev": [103625, 103606, 103607], "entries": [{"id": 127874, "definitionId": 132683, "maxRanks": 1, "type": "passive", "name": "Totemic Surge", "spellId": 381867, "icon": "spell_nature_agitatingtotem", "index": 100}]}, {"id": 103628, "name": "Seasoned Winds", "type": "single", "posX": 6600, "posY": 5400, "reqPoints": 20, "maxRanks": 1, "next": [103595], "prev": [103606], "entries": [{"id": 127910, "definitionId": 132719, "maxRanks": 1, "type": "passive", "name": "Seasoned Winds", "spellId": 355630, "icon": "spell_nature_cyclone", "index": 200}]}, {"id": 103587, "name": "Mana Spring", "type": "single", "posX": 2400, "posY": 6000, "reqPoints": 20, "maxRanks": 1, "next": [103620], "prev": [103589, 103626], "entries": [{"id": 127860, "definitionId": 132669, "maxRanks": 1, "type": "passive", "name": "Mana Spring", "spellId": 381930, "icon": "spell_nature_manaregentotem", "index": 200}]}, {"id": 103621, "name": "Thundershock / Traveling Storms", "type": "choice", "posX": 3600, "posY": 6000, "reqPoints": 20, "maxRanks": 1, "next": [103629], "prev": [103603], "entries": [{"id": 127901, "definitionId": 132710, "maxRanks": 1, "type": "passive", "name": "Thundershock", "spellId": 378779, "icon": "ability_thunderking_thunderstruck", "index": 200}, {"id": 127900, "definitionId": 132709, "maxRanks": 1, "type": "passive", "name": "Traveling Storms", "spellId": 204403, "icon": "spell_shaman_thunderstorm", "index": 300}]}, {"id": 103609, "name": "Poison Cleansing Totem", "type": "single", "posX": 4800, "posY": 6000, "reqPoints": 20, "maxRanks": 1, "next": [103629], "prev": [103625, 103586, 103599], "entries": [{"id": 127885, "definitionId": 132694, "maxRanks": 1, "type": "active", "name": "Poison Cleansing Totem", "spellId": 383013, "icon": "spell_nature_poisoncleansingtotem", "index": 100}]}, {"id": 103595, "name": "Totemic Recall", "type": "single", "posX": 6000, "posY": 6000, "reqPoints": 20, "maxRanks": 1, "next": [103592], "prev": [103628, 103599], "entries": [{"id": 127870, "definitionId": 132679, "maxRanks": 1, "type": "active", "name": "Totemic Recall", "spellId": 108285, "icon": "ability_shaman_multitotemactivation", "index": 100}]}, {"id": 103620, "name": "Nature's Swiftness", "type": "single", "posX": 1800, "posY": 6600, "reqPoints": 20, "maxRanks": 1, "next": [], "prev": [103626, 103587], "entries": [{"id": 127899, "definitionId": 132708, "maxRanks": 1, "type": "active", "name": "Nature's Swiftness", "spellId": 378081, "icon": "spell_nature_ravenform", "index": 100}]}, {"id": 103629, "name": "Stone Bulwark Totem", "type": "single", "posX": 4200, "posY": 6600, "reqPoints": 20, "maxRanks": 1, "next": [], "prev": [103586, 103621, 103609], "entries": [{"id": 127911, "definitionId": 132720, "maxRanks": 1, "type": "active", "name": "Stone Bulwark Totem", "spellId": 108270, "icon": "ability_shaman_stonebulwark", "index": 100}]}, {"id": 103592, "name": "Call of the Elements / Creation Core", "type": "choice", "posX": 6000, "posY": 6600, "reqPoints": 20, "maxRanks": 1, "next": [], "prev": [103595], "entries": [{"id": 127867, "definitionId": 132676, "maxRanks": 1, "type": "passive", "name": "Call of the Elements", "spellId": 383011, "icon": "ability_shaman_multitotemactivation", "index": 200}, {"id": 127866, "definitionId": 132675, "maxRanks": 1, "type": "passive", "name": "Creation Core", "spellId": 383012, "icon": "inv_artifact_xp03", "index": 300}]}], "specNodes": [{"id": 80984, "name": "Earth Shock / Elemental Blast", "type": "choice", "posX": 12600, "posY": 1200, "maxRanks": 1, "entryNode": true, "next": [80985, 80983, 80981], "prev": [], "entries": [{"id": 101854, "definitionId": 106811, "maxRanks": 1, "type": "active", "name": "Earth Shock", "spellId": 8042, "icon": "spell_nature_earthshock", "index": 100}, {"id": 127924, "definitionId": 132733, "maxRanks": 1, "type": "active", "name": "Elemental Blast", "spellId": 117014, "icon": "shaman_talent_elementalblast", "index": 200}]}, {"id": 80985, "name": "Earthquake / Earthquake", "type": "choice", "posX": 12000, "posY": 1800, "maxRanks": 1, "next": [80990], "prev": [80984], "entries": [{"id": 101855, "definitionId": 106814, "maxRanks": 1, "type": "active", "name": "Earthquake", "spellId": 462620, "icon": "spell_shaman_earthquake", "index": 100}, {"id": 127925, "definitionId": 132734, "maxRanks": 1, "type": "active", "name": "Earthquake", "spellId": 61882, "icon": "spell_shaman_earthquake", "index": 200}]}, {"id": 80983, "name": "Elemental Fury", "type": "single", "posX": 12600, "posY": 1800, "maxRanks": 1, "next": [81000], "prev": [80984], "entries": [{"id": 101853, "definitionId": 106810, "maxRanks": 1, "type": "passive", "name": "Elemental Fury", "spellId": 60188, "icon": "spell_fire_volcano", "index": 100}]}, {"id": 80981, "name": "Fire Elemental / Storm Elemental", "type": "choice", "posX": 13200, "posY": 1800, "maxRanks": 1, "next": [80999], "prev": [80984], "entries": [{"id": 101850, "definitionId": 106837, "maxRanks": 1, "type": "active", "name": "Fire Elemental", "spellId": 198067, "icon": "spell_fire_elemental_totem", "index": 100}, {"id": 101849, "definitionId": 106836, "maxRanks": 1, "type": "active", "name": "Storm Elemental", "spellId": 192249, "icon": "inv_stormelemental", "index": 200}]}, {"id": 80990, "name": "Flash of Lightning", "type": "single", "posX": 11400, "posY": 2400, "maxRanks": 1, "next": [80997, 103635], "prev": [80985], "entries": [{"id": 101861, "definitionId": 106843, "maxRanks": 1, "type": "passive", "name": "Flash of Lightning", "spellId": 381936, "icon": "spell_lightning_lightningbolt01", "index": 100}]}, {"id": 81000, "name": "Aftershock / Surge of Power", "type": "choice", "posX": 12600, "posY": 2400, "maxRanks": 1, "next": [80988], "prev": [80983], "entries": [{"id": 101874, "definitionId": 106831, "maxRanks": 1, "type": "passive", "name": "Aftershock", "spellId": 273221, "icon": "spell_nature_stormreach", "index": 100}, {"id": 101873, "definitionId": 106830, "maxRanks": 1, "type": "passive", "name": "Surge of Power", "spellId": 262303, "icon": "spell_nature_shamanrage", "index": 200}]}, {"id": 80999, "name": "Echo of the Elements", "type": "single", "posX": 13800, "posY": 2400, "maxRanks": 1, "next": [81004], "prev": [80981], "entries": [{"id": 101872, "definitionId": 106832, "maxRanks": 1, "type": "passive", "name": "Echo of the Elements", "spellId": 333919, "icon": "ability_shaman_echooftheelements", "index": 100}]}, {"id": 80997, "name": "Icefury", "type": "single", "posX": 10800, "posY": 3000, "maxRanks": 1, "next": [103638], "prev": [80990], "entries": [{"id": 101870, "definitionId": 106817, "maxRanks": 1, "type": "passive", "name": "Icefury", "spellId": 462816, "icon": "spell_frost_iceshard", "index": 100}]}, {"id": 80988, "name": "Stormkeeper", "type": "single", "posX": 12600, "posY": 3000, "maxRanks": 1, "next": [81016, 103639, 80998], "prev": [81000], "entries": [{"id": 101859, "definitionId": 106819, "maxRanks": 1, "type": "active", "name": "Stormkeeper", "spellId": 191634, "icon": "ability_thunderking_lightningwhip", "index": 100}]}, {"id": 81004, "name": "Master of the Elements", "type": "single", "posX": 14400, "posY": 3000, "maxRanks": 1, "next": [103630], "prev": [80999], "entries": [{"id": 101879, "definitionId": 106829, "maxRanks": 1, "type": "passive", "name": "Master of the Elements", "spellId": 16166, "icon": "spell_nature_elementalabsorption", "index": 100}]}, {"id": 103638, "name": "Fusion of Elements", "type": "single", "posX": 10800, "posY": 3600, "reqPoints": 8, "maxRanks": 1, "next": [80996], "prev": [80997], "entries": [{"id": 127919, "definitionId": 132728, "maxRanks": 1, "type": "passive", "name": "Fusion of Elements", "spellId": 462840, "icon": "inv_10_enchanting2_elementalswirl_color1", "index": 100}]}, {"id": 103635, "name": "Storm Frenzy", "type": "single", "posX": 11400, "posY": 3600, "reqPoints": 8, "maxRanks": 1, "next": [80996, 103631, 80995], "prev": [80990], "entries": [{"id": 127917, "definitionId": 132726, "maxRanks": 1, "type": "passive", "name": "Storm Frenzy", "spellId": 462695, "icon": "spell_nature_callstorm", "index": 100}]}, {"id": 81016, "name": "Swelling Maelstrom", "type": "single", "posX": 12000, "posY": 3600, "reqPoints": 8, "maxRanks": 1, "next": [103631], "prev": [80988], "entries": [{"id": 101893, "definitionId": 106815, "maxRanks": 1, "type": "passive", "name": "Swelling Maelstrom", "spellId": 381707, "icon": "spell_shaman_maelstromweapon", "index": 100}]}, {"id": 103639, "name": "Primordial Fury", "type": "single", "posX": 12600, "posY": 3600, "reqPoints": 8, "maxRanks": 1, "next": [103631, 81015, 81009], "prev": [80988], "entries": [{"id": 127920, "definitionId": 132729, "maxRanks": 1, "type": "passive", "name": "Primordial Fury", "spellId": 378193, "icon": "inv_10_elementalshardfoozles_primordial", "index": 100}]}, {"id": 80998, "name": "Fury of the Storms / Herald of the Storms", "type": "choice", "posX": 13200, "posY": 3600, "reqPoints": 8, "maxRanks": 1, "next": [81009, 103633], "prev": [80988], "entries": [{"id": 101871, "definitionId": 106816, "maxRanks": 1, "type": "passive", "name": "Fury of the Storms", "spellId": 191717, "icon": "ability_thunderking_overcharge", "index": 100}, {"id": 128223, "definitionId": 133030, "maxRanks": 1, "type": "passive", "name": "Herald of the Storms", "spellId": 468571, "icon": "achievement_raidprimalist_windelemental", "index": 200}]}, {"id": 103630, "name": "Elemental Unity", "type": "single", "posX": 14400, "posY": 3600, "reqPoints": 8, "maxRanks": 1, "next": [103633, 81010], "prev": [81004], "entries": [{"id": 127912, "definitionId": 132721, "maxRanks": 1, "type": "passive", "name": "Elemental Unity", "spellId": 462866, "icon": "inv_10_elementalspiritfoozles_air", "index": 100}]}, {"id": 80996, "name": "Flux Melting", "type": "single", "posX": 10800, "posY": 4200, "reqPoints": 8, "maxRanks": 1, "next": [80995, 80993], "prev": [103635, 103638], "entries": [{"id": 101869, "definitionId": 106823, "maxRanks": 1, "type": "passive", "name": "Flux Melting", "spellId": 381776, "icon": "spell_frostfire-orb", "index": 100}]}, {"id": 103631, "name": "Lightning Capacitor", "type": "single", "posX": 12000, "posY": 4200, "reqPoints": 8, "maxRanks": 1, "next": [80995, 103636, 81013], "prev": [103635, 81016, 103639], "entries": [{"id": 127913, "definitionId": 132722, "maxRanks": 1, "type": "passive", "name": "Lightning Capacitor", "spellId": 462862, "icon": "spell_nature_lightningshield", "index": 100}]}, {"id": 81015, "name": "Power of the Maelstrom", "type": "single", "posX": 12600, "posY": 4200, "reqPoints": 8, "maxRanks": 1, "next": [81013, 81005], "prev": [103639], "entries": [{"id": 101892, "definitionId": 106824, "maxRanks": 1, "type": "passive", "name": "Power of the Maelstrom", "spellId": 191861, "icon": "spell_fire_masterofelements", "index": 100}]}, {"id": 81009, "name": "Improved Flametongue Weapon", "type": "single", "posX": 13200, "posY": 4200, "reqPoints": 8, "maxRanks": 1, "next": [81005], "prev": [103639, 80998], "entries": [{"id": 101886, "definitionId": 106853, "maxRanks": 1, "type": "passive", "name": "Improved Flametongue Weapon", "spellId": 382027, "icon": "spell_fire_flametounge", "index": 100}]}, {"id": 103633, "name": "Everlasting Elements", "type": "single", "posX": 13800, "posY": 4200, "reqPoints": 8, "maxRanks": 1, "next": [81005, 103634, 81010], "prev": [103630, 80998], "entries": [{"id": 127915, "definitionId": 132724, "maxRanks": 1, "type": "passive", "name": "Everlasting Elements", "spellId": 462867, "icon": "spell_nature_earthelemental_totem", "index": 100}]}, {"id": 80995, "name": "Earthshatter", "type": "single", "posX": 11400, "posY": 4800, "reqPoints": 8, "maxRanks": 1, "next": [80993, 81003], "prev": [103635, 103631, 80996], "entries": [{"id": 101867, "definitionId": 106821, "maxRanks": 1, "type": "passive", "name": "Earthshatter", "spellId": 468626, "icon": "spell_nature_earthquake", "index": 100}]}, {"id": 103636, "name": "Thunderstrike Ward", "type": "single", "posX": 12000, "posY": 4800, "reqPoints": 8, "maxRanks": 1, "next": [81003], "prev": [103631], "entries": [{"id": 127918, "definitionId": 132727, "maxRanks": 1, "type": "active", "name": "Thunderstrike Ward", "spellId": 462757, "icon": "inv_armorkit_lightning_imbued", "index": 100}]}, {"id": 81013, "name": "Echo Chamber", "type": "single", "posX": 12600, "posY": 4800, "reqPoints": 8, "maxRanks": 1, "next": [81003, 80989, 81008], "prev": [103631, 81015], "entries": [{"id": 101890, "definitionId": 106839, "maxRanks": 1, "type": "passive", "name": "Echo Chamber", "spellId": 382032, "icon": "spell_nature_lightningoverload", "index": 100}]}, {"id": 81005, "name": "Searing Flames", "type": "single", "posX": 13200, "posY": 4800, "reqPoints": 8, "maxRanks": 1, "next": [81008, 81014], "prev": [81015, 81009, 103633], "entries": [{"id": 101880, "definitionId": 106847, "maxRanks": 1, "type": "passive", "name": "Searing Flames", "spellId": 381782, "icon": "inv_offhand_1h_artifactdoomhammer_d_01", "index": 100}]}, {"id": 103634, "name": "Earthen Rage", "type": "single", "posX": 13800, "posY": 4800, "reqPoints": 8, "maxRanks": 1, "next": [81014], "prev": [103633], "entries": [{"id": 127916, "definitionId": 132725, "maxRanks": 1, "type": "passive", "name": "Earthen Rage", "spellId": 170374, "icon": "ability_earthen_pillar", "index": 100}]}, {"id": 81010, "name": "Flames of the Cauldron", "type": "single", "posX": 14400, "posY": 4800, "reqPoints": 8, "maxRanks": 1, "next": [81014], "prev": [103630, 103633], "entries": [{"id": 101887, "definitionId": 106854, "maxRanks": 1, "type": "passive", "name": "Flames of the Cauldron", "spellId": 378266, "icon": "inv_misc_cauldron_fire", "index": 100}]}, {"id": 80993, "name": "Elemental Equilibrium", "type": "single", "posX": 10800, "posY": 5400, "reqPoints": 20, "maxRanks": 1, "next": [81012], "prev": [80995, 80996], "entries": [{"id": 101865, "definitionId": 106841, "maxRanks": 1, "type": "passive", "name": "Elemental Equilibrium", "spellId": 378271, "icon": "ability_shaman_ascendance", "index": 100}]}, {"id": 81003, "name": "Eye of the Storm", "type": "single", "posX": 12000, "posY": 5400, "reqPoints": 20, "maxRanks": 1, "next": [81012, 81002], "prev": [103636, 81013, 80995], "entries": [{"id": 101877, "definitionId": 106827, "maxRanks": 1, "type": "passive", "name": "Eye of the Storm", "spellId": 381708, "icon": "spell_shadow_soulleech_2", "index": 300}]}, {"id": 80989, "name": "Ascendance", "type": "single", "posX": 12600, "posY": 5400, "reqPoints": 20, "maxRanks": 1, "next": [81002, 103640, 81006], "prev": [81013], "entries": [{"id": 101860, "definitionId": 106820, "maxRanks": 1, "type": "active", "name": "Ascendance", "spellId": 114050, "icon": "spell_fire_elementaldevastation", "index": 100}]}, {"id": 81008, "name": "Echo of the Elementals", "type": "single", "posX": 13200, "posY": 5400, "reqPoints": 20, "maxRanks": 1, "next": [81006, 81007], "prev": [81013, 81005], "entries": [{"id": 101885, "definitionId": 106852, "maxRanks": 1, "type": "passive", "name": "Echo of the Elementals", "spellId": 462864, "icon": "inv_10_elementalspiritfoozles_fire", "index": 200}]}, {"id": 81014, "name": "Primordial Wave", "type": "single", "posX": 13800, "posY": 5400, "reqPoints": 20, "maxRanks": 1, "next": [81007, 80978], "prev": [81005, 81010, 103634], "entries": [{"id": 101891, "definitionId": 106840, "maxRanks": 1, "type": "active", "name": "Primordial Wave", "spellId": 375982, "icon": "inv_ability_shaman_primordialwave", "index": 100}]}, {"id": 81012, "name": "Lightning Rod", "type": "single", "posX": 11400, "posY": 6000, "reqPoints": 20, "maxRanks": 1, "next": [80991, 103641], "prev": [81003, 80993], "entries": [{"id": 101889, "definitionId": 106838, "maxRanks": 1, "type": "passive", "name": "Lightning Rod", "spellId": 210689, "icon": "inv_rod_enchantedcobalt", "index": 100}]}, {"id": 81002, "name": "Mountains Will Fall", "type": "single", "posX": 12000, "posY": 6000, "reqPoints": 20, "maxRanks": 1, "next": [103641, 80992], "prev": [81003, 80989], "entries": [{"id": 101876, "definitionId": 106826, "maxRanks": 1, "type": "passive", "name": "Mountains Will Fall", "spellId": 381726, "icon": "inv_elementalearth2", "index": 100}]}, {"id": 103640, "name": "First Ascendant / Preeminence", "type": "choice", "posX": 12600, "posY": 6000, "reqPoints": 20, "maxRanks": 1, "next": [80992, 103632], "prev": [80989], "entries": [{"id": 127921, "definitionId": 132730, "maxRanks": 1, "type": "passive", "name": "First Ascendant", "spellId": 462440, "icon": "spell_shaman_astralshift", "index": 100}, {"id": 128224, "definitionId": 133031, "maxRanks": 1, "type": "passive", "name": "Preeminence", "spellId": 462443, "icon": "spell_shaman_improvedreincarnation", "index": 200}]}, {"id": 81006, "name": "Erupting Lava", "type": "single", "posX": 13200, "posY": 6000, "reqPoints": 20, "maxRanks": 1, "next": [103632], "prev": [81008, 80989], "entries": [{"id": 101881, "definitionId": 106848, "maxRanks": 1, "type": "passive", "name": "Erupting Lava", "spellId": 468574, "icon": "ability_rhyolith_lavapool", "index": 300}]}, {"id": 81007, "name": "Magma Chamber", "type": "single", "posX": 13800, "posY": 6000, "reqPoints": 20, "maxRanks": 1, "next": [103632, 103637], "prev": [81008, 81014], "entries": [{"id": 101883, "definitionId": 106850, "maxRanks": 1, "type": "passive", "name": "Magma Chamber", "spellId": 381932, "icon": "ability_rhyolith_magmaflow_whole", "index": 100}]}, {"id": 80978, "name": "Splintered Elements", "type": "single", "posX": 14400, "posY": 6000, "reqPoints": 20, "maxRanks": 1, "next": [103637], "prev": [81014], "entries": [{"id": 101844, "definitionId": 106856, "maxRanks": 1, "type": "passive", "name": "Splintered Elements", "spellId": 382042, "icon": "spell_nature_elementalprecision_1", "index": 300}]}, {"id": 80991, "name": "Charged Conduit", "type": "single", "posX": 10800, "posY": 6600, "reqPoints": 20, "maxRanks": 1, "next": [], "prev": [81012], "entries": [{"id": 101862, "definitionId": 106844, "maxRanks": 1, "type": "passive", "name": "Charged Conduit", "spellId": 468625, "icon": "ability_thunderking_thunderstruck", "index": 100}]}, {"id": 103641, "name": "Echoes of Great Sundering", "type": "single", "posX": 12000, "posY": 6600, "reqPoints": 20, "maxRanks": 1, "next": [], "prev": [81012, 81002], "entries": [{"id": 127922, "definitionId": 132731, "maxRanks": 1, "type": "passive", "name": "Echoes of Great Sundering", "spellId": 384087, "icon": "spell_shaman_earthquake", "index": 300}]}, {"id": 80992, "name": "Deeply Rooted Elements", "type": "single", "posX": 12600, "posY": 6600, "reqPoints": 20, "maxRanks": 1, "next": [], "prev": [81002, 103640], "entries": [{"id": 101864, "definitionId": 106846, "maxRanks": 1, "type": "passive", "name": "Deeply Rooted Elements", "spellId": 378270, "icon": "inv_misc_herb_liferoot_stem", "index": 100}]}, {"id": 103632, "name": "Primal Elementalist", "type": "single", "posX": 13200, "posY": 6600, "reqPoints": 20, "maxRanks": 1, "next": [], "prev": [103640, 81007, 81006], "entries": [{"id": 127914, "definitionId": 132723, "maxRanks": 1, "type": "passive", "name": "Primal Elementalist", "spellId": 117013, "icon": "shaman_talent_primalelementalist", "index": 100}]}, {"id": 103637, "name": "Liquid Magma Totem", "type": "single", "posX": 14400, "posY": 6600, "reqPoints": 20, "maxRanks": 1, "next": [], "prev": [81007, 80978], "entries": [{"id": 101884, "definitionId": 106851, "maxRanks": 1, "type": "active", "name": "Liquid Magma Totem", "spellId": 192222, "icon": "spell_shaman_spewlava", "index": 100}]}], "heroNodes": [{"id": 94888, "name": "Call of the Ancestors", "type": "single", "posX": 8100, "posY": 1200, "maxRanks": 1, "entryNode": true, "subTreeId": 56, "requiresNode": 81037, "next": [94862, 94869, 94884], "prev": [], "entries": [{"id": 117485, "definitionId": 122497, "maxRanks": 1, "type": "passive", "name": "Call of the Ancestors", "spellId": 443450, "icon": "ability_racial_ancestralcall", "index": 100}], "freeNode": true}, {"id": 94862, "name": "Latent Wisdom / Ancient Fellowship", "type": "choice", "posX": 7500, "posY": 1800, "maxRanks": 1, "subTreeId": 56, "requiresNode": 81014, "next": [94887], "prev": [94888], "entries": [{"id": 117459, "definitionId": 122471, "maxRanks": 1, "type": "passive", "name": "Latent Wisdom", "spellId": 443449, "icon": "spell_holy_spiritualguidence", "index": 100}, {"id": 123632, "definitionId": 128470, "maxRanks": 1, "type": "passive", "name": "Ancient Fellowship", "spellId": 443423, "icon": "spell_shaman_astralshift", "index": 200}]}, {"id": 94884, "name": "Heed My Call / Routine Communication", "type": "choice", "posX": 8100, "posY": 1800, "maxRanks": 1, "subTreeId": 56, "next": [94860], "prev": [94888], "entries": [{"id": 117481, "definitionId": 122493, "maxRanks": 1, "type": "passive", "name": "Heed My Call", "spellId": 443444, "icon": "spell_unused2", "index": 100}, {"id": 123630, "definitionId": 128468, "maxRanks": 1, "type": "passive", "name": "Routine Communication", "spellId": 443445, "icon": "spell_nature_undyingstrength", "index": 200}]}, {"id": 94869, "name": "Elemental Reverb", "type": "single", "posX": 8700, "posY": 1800, "maxRanks": 1, "subTreeId": 56, "next": [94861], "prev": [94888], "entries": [{"id": 117466, "definitionId": 122478, "maxRanks": 1, "type": "passive", "name": "Elemental Reverb", "spellId": 443418, "icon": "ability_shaman_echooftheelements", "index": 100}]}, {"id": 94887, "name": "Offering from Beyond", "type": "single", "posX": 7500, "posY": 2400, "maxRanks": 1, "subTreeId": 56, "requiresNode": 81014, "next": [94858], "prev": [94862], "entries": [{"id": 117484, "definitionId": 122496, "maxRanks": 1, "type": "passive", "name": "Offering from Beyond", "spellId": 443451, "icon": "spell_shaman_blessingoftheeternals", "index": 100}]}, {"id": 94860, "name": "Primordial Capacity", "type": "single", "posX": 8100, "posY": 2400, "maxRanks": 1, "subTreeId": 56, "next": [94883], "prev": [94884], "entries": [{"id": 117457, "definitionId": 122469, "maxRanks": 1, "type": "passive", "name": "Primordial Capacity", "spellId": 443448, "icon": "ability_monk_chiswirl", "index": 100}]}, {"id": 94861, "name": "Spiritwalker's Momentum", "type": "single", "posX": 8700, "posY": 2400, "maxRanks": 1, "subTreeId": 56, "next": [94875], "prev": [94869], "entries": [{"id": 117458, "definitionId": 122470, "maxRanks": 1, "type": "passive", "name": "Spiritwalker's Momentum", "spellId": 443425, "icon": "spell_shaman_spiritwalkersgrace", "index": 100}]}, {"id": 94858, "name": "Natural Harmony / Earthen Communion", "type": "choice", "posX": 7500, "posY": 3000, "maxRanks": 1, "subTreeId": 56, "next": [94894], "prev": [94887], "entries": [{"id": 117455, "definitionId": 122467, "maxRanks": 1, "type": "passive", "name": "Natural Harmony", "spellId": 443442, "icon": "spell_nature_natureguardian", "index": 100}, {"id": 123631, "definitionId": 128469, "maxRanks": 1, "type": "passive", "name": "Earthen Communion", "spellId": 443441, "icon": "spell_nature_skinofearth", "index": 200}]}, {"id": 94883, "name": "Maelstrom Supremacy", "type": "single", "posX": 8100, "posY": 3000, "maxRanks": 1, "subTreeId": 56, "next": [94894], "prev": [94860], "entries": [{"id": 117480, "definitionId": 122492, "maxRanks": 1, "type": "passive", "name": "Maelstrom Supremacy", "spellId": 443447, "icon": "spell_shadow_soulleech_2", "index": 100}]}, {"id": 94875, "name": "Final Calling", "type": "single", "posX": 8700, "posY": 3000, "maxRanks": 1, "subTreeId": 56, "next": [94894], "prev": [94861], "entries": [{"id": 117472, "definitionId": 122484, "maxRanks": 1, "type": "passive", "name": "Final Calling", "spellId": 443446, "icon": "spell_shaman_ancestralawakening", "index": 100}]}, {"id": 94894, "name": "Ancestral Swiftness", "type": "single", "posX": 8100, "posY": 3600, "maxRanks": 1, "subTreeId": 56, "next": [], "prev": [94883, 94858, 94875], "entries": [{"id": 117491, "definitionId": 122503, "maxRanks": 1, "type": "active", "name": "Ancestral Swiftness", "spellId": 448861, "visibleSpellId": 443454, "icon": "inv_ability_farseershaman_ancestralswiftness", "index": 100}]}, {"id": 94892, "name": "Tempest", "type": "single", "posX": 8100, "posY": 4200, "maxRanks": 1, "entryNode": true, "subTreeId": 55, "next": [94886, 94893, 94863], "prev": [], "entries": [{"id": 117489, "definitionId": 122501, "maxRanks": 1, "type": "passive", "name": "Tempest", "spellId": 454009, "icon": "inv_ability_stormcallershaman_tempest", "index": 100}], "freeNode": true}, {"id": 94886, "name": "Unlimited Power", "type": "single", "posX": 7500, "posY": 4800, "maxRanks": 1, "subTreeId": 55, "next": [94873], "prev": [94892], "entries": [{"id": 117483, "definitionId": 122495, "maxRanks": 1, "type": "passive", "name": "Unlimited Power", "spellId": 454391, "icon": "spell_nature_purge", "index": 100}]}, {"id": 94893, "name": "Stormcaller", "type": "single", "posX": 8100, "posY": 4800, "maxRanks": 1, "subTreeId": 55, "next": [94885], "prev": [94892], "entries": [{"id": 117490, "definitionId": 122502, "maxRanks": 1, "type": "passive", "name": "Stormcaller", "spellId": 454021, "icon": "ability_vehicle_electrocharge", "index": 100}]}, {"id": 94863, "name": "Lightning Conduit / Electroshock", "type": "choice", "posX": 8700, "posY": 4800, "maxRanks": 1, "subTreeId": 55, "next": [94889], "prev": [94892], "entries": [{"id": 117460, "definitionId": 122472, "maxRanks": 1, "type": "passive", "name": "Lightning Conduit", "spellId": 467778, "icon": "spell_shaman_staticshock", "index": 100}, {"id": 128226, "definitionId": 133033, "maxRanks": 1, "type": "passive", "name": "Electroshock", "spellId": 454022, "icon": "ability_thunderking_overcharge", "index": 200}]}, {"id": 94873, "name": "Storm Swell / Supercharge", "type": "choice", "posX": 7500, "posY": 5400, "maxRanks": 1, "subTreeId": 55, "next": [94870], "prev": [94886], "entries": [{"id": 117470, "definitionId": 122482, "maxRanks": 1, "type": "passive", "name": "Storm Swell", "spellId": 455088, "icon": "spell_nature_unrelentingstorm", "index": 100}, {"id": 128225, "definitionId": 133032, "maxRanks": 1, "type": "passive", "name": "Supercharge", "spellId": 455110, "icon": "inv_misc_stormlordsfavor", "index": 200}]}, {"id": 94885, "name": "Arc Discharge", "type": "single", "posX": 8100, "posY": 5400, "maxRanks": 1, "subTreeId": 55, "next": [94868], "prev": [94893], "entries": [{"id": 117482, "definitionId": 122494, "maxRanks": 1, "type": "passive", "name": "Arc Discharge", "spellId": 455096, "icon": "ability_thunderking_balllightning", "index": 100}]}, {"id": 94889, "name": "Rolling Thunder", "type": "single", "posX": 8700, "posY": 5400, "maxRanks": 1, "subTreeId": 55, "next": [94880], "prev": [94863], "entries": [{"id": 117486, "definitionId": 122498, "maxRanks": 1, "type": "passive", "name": "Rolling Thunder", "spellId": 454026, "icon": "spell_lightning_lightningbolt01", "index": 100}]}, {"id": 94870, "name": "Voltaic Surge", "type": "single", "posX": 7500, "posY": 6000, "maxRanks": 1, "subTreeId": 55, "next": [94867], "prev": [94873], "entries": [{"id": 117467, "definitionId": 122479, "maxRanks": 1, "type": "passive", "name": "Voltaic Surge", "spellId": 454919, "icon": "spell_nature_callstorm", "index": 100}]}, {"id": 94868, "name": "Conductive Energy", "type": "single", "posX": 8100, "posY": 6000, "maxRanks": 1, "subTreeId": 55, "next": [94867], "prev": [94885], "entries": [{"id": 117465, "definitionId": 122477, "maxRanks": 1, "type": "passive", "name": "Conductive Energy", "spellId": 455123, "icon": "inv_rod_enchantedcobalt", "index": 100}]}, {"id": 94880, "name": "Nature's Protection / Surging Currents", "type": "choice", "posX": 8700, "posY": 6000, "maxRanks": 1, "subTreeId": 55, "next": [94867], "prev": [94889], "entries": [{"id": 117477, "definitionId": 122489, "maxRanks": 1, "type": "passive", "name": "Nature's Protection", "spellId": 454027, "icon": "spell_nature_lightningshield", "index": 100}, {"id": 125617, "definitionId": 130449, "maxRanks": 1, "type": "passive", "name": "Surging Currents", "spellId": 454372, "icon": "ability_thunderking_thunderstruck", "index": 200}]}, {"id": 94867, "name": "Awakening Storms", "type": "single", "posX": 8100, "posY": 6600, "maxRanks": 1, "subTreeId": 55, "next": [], "prev": [94868, 94870, 94880], "entries": [{"id": 117464, "definitionId": 122476, "maxRanks": 1, "type": "passive", "name": "Awakening Storms", "spellId": 455129, "icon": "spell_nature_stormreach", "index": 100}]}], "subTreeNodes": [{"id": 99845, "name": "Farseer / Stormbringer", "type": "subtree", "posX": 7200, "posY": 600, "entryNode": true, "next": [], "prev": [], "entries": [{"id": 123377, "type": "subtree", "name": "Farseer", "traitSubTreeId": 56, "traitTreeId": 786, "atlasMemberName": "talents-heroclass-shaman-farseer", "nodes": [94888, 94862, 94884, 94869, 94887, 94860, 94861, 94858, 94883, 94875, 94894]}, {"id": 123376, "type": "subtree", "name": "Stormbringer", "traitSubTreeId": 55, "traitTreeId": 786, "atlasMemberName": "talents-heroclass-shaman-stormbringer", "nodes": [94892, 94886, 94893, 94863, 94873, 94885, 94889, 94870, 94868, 94880, 94867]}]}], "fullNodeOrder": [80938, 80939, 80941, 80942, 80943, 80944, 80945, 80947, 80948, 80949, 80950, 80951, 80953, 80954, 80955, 80956, 80957, 80958, 80959, 80960, 80961, 80962, 80963, 80964, 80965, 80966, 80967, 80968, 80969, 80970, 80971, 80972, 80973, 80974, 80975, 80976, 80978, 80981, 80983, 80984, 80985, 80988, 80989, 80990, 80991, 80992, 80993, 80995, 80996, 80997, 80998, 80999, 81000, 81002, 81003, 81004, 81005, 81006, 81007, 81008, 81009, 81010, 81012, 81013, 81014, 81015, 81016, 81018, 81019, 81021, 81022, 81024, 81026, 81027, 81031, 81032, 81033, 81036, 81037, 81038, 81039, 81040, 81041, 81042, 81043, 81044, 81045, 81046, 81047, 81048, 81049, 81050, 81051, 81052, 81055, 81073, 92219, 92675, 92677, 92681, 94858, 94859, 94860, 94861, 94862, 94863, 94866, 94867, 94868, 94869, 94870, 94871, 94872, 94873, 94874, 94875, 94877, 94879, 94880, 94881, 94882, 94883, 94884, 94885, 94886, 94887, 94888, 94889, 94890, 94891, 94892, 94893, 94894, 99845, 99846, 99847, 103427, 103428, 103429, 103430, 103432, 103433, 103434, 103435, 103436, 103579, 103581, 103582, 103583, 103584, 103585, 103586, 103587, 103588, 103589, 103590, 103591, 103592, 103593, 103594, 103595, 103596, 103597, 103598, 103599, 103600, 103601, 103602, 103603, 103604, 103605, 103606, 103607, 103608, 103609, 103610, 103611, 103612, 103613, 103614, 103615, 103616, 103617, 103618, 103619, 103620, 103621, 103622, 103623, 103624, 103625, 103626, 103627, 103628, 103629, 103630, 103631, 103632, 103633, 103634, 103635, 103636, 103637, 103638, 103639, 103640, 103641, 103642, 103810, 103848, 103871, 103915]}